{
"meta":{"test_sets":[],"test_metrics":[],"learn_metrics":[{"best_value":"Min","name":"MultiClass"}],"launch_mode":"Train","parameters":"","iteration_count":1000,"learn_sets":["learn"],"name":"experiment"},
"iterations":[
{"learn":[1.752872],"iteration":0,"passed_time":0.009849004213,"remaining_time":9.839155209},
{"learn":[1.600810638],"iteration":1,"passed_time":0.01895874747,"remaining_time":9.460414985},
{"learn":[1.48279102],"iteration":2,"passed_time":0.02958940935,"remaining_time":9.833547042},
{"learn":[1.394480728],"iteration":3,"passed_time":0.03931924311,"remaining_time":9.790491535},
{"learn":[1.31684268],"iteration":4,"passed_time":0.04876231532,"remaining_time":9.703700748},
{"learn":[1.25369733],"iteration":5,"passed_time":0.05849701556,"remaining_time":9.691005577},
{"learn":[1.198219335],"iteration":6,"passed_time":0.06870203285,"remaining_time":9.745874089},
{"learn":[1.153512595],"iteration":7,"passed_time":0.07812306589,"remaining_time":9.687260171},
{"learn":[1.109382559],"iteration":8,"passed_time":0.08751646582,"remaining_time":9.636535292},
{"learn":[1.068002602],"iteration":9,"passed_time":0.09654189563,"remaining_time":9.557647667},
{"learn":[1.035732705],"iteration":10,"passed_time":0.105644395,"remaining_time":9.498391513},
{"learn":[1.000700235],"iteration":11,"passed_time":0.1151055632,"remaining_time":9.477024701},
{"learn":[0.9720398593],"iteration":12,"passed_time":0.1243899689,"remaining_time":9.444069179},
{"learn":[0.9438250462],"iteration":13,"passed_time":0.1335226313,"remaining_time":9.403808176},
{"learn":[0.9178564597],"iteration":14,"passed_time":0.1425843989,"remaining_time":9.363042193},
{"learn":[0.8981937117],"iteration":15,"passed_time":0.1531017776,"remaining_time":9.415759322},
{"learn":[0.8762056516],"iteration":16,"passed_time":0.163369995,"remaining_time":9.44662971},
{"learn":[0.8569740198],"iteration":17,"passed_time":0.1730416026,"remaining_time":9.440380765},
{"learn":[0.8387828338],"iteration":18,"passed_time":0.1818347713,"remaining_time":9.388416349},
{"learn":[0.8234372389],"iteration":19,"passed_time":0.1917029598,"remaining_time":9.393445029},
{"learn":[0.8094287772],"iteration":20,"passed_time":0.202308286,"remaining_time":9.431419617},
{"learn":[0.7954640881],"iteration":21,"passed_time":0.2113850021,"remaining_time":9.397024186},
{"learn":[0.7825992315],"iteration":22,"passed_time":0.2209906798,"remaining_time":9.387299746},
{"learn":[0.7715875061],"iteration":23,"passed_time":0.2318249998,"remaining_time":9.42754999},
{"learn":[0.7590125898],"iteration":24,"passed_time":0.2433636362,"remaining_time":9.491181811},
{"learn":[0.7481220475],"iteration":25,"passed_time":0.2532708573,"remaining_time":9.487915963},
{"learn":[0.7372971182],"iteration":26,"passed_time":0.2642118699,"remaining_time":9.52141294},
{"learn":[0.7284674055],"iteration":27,"passed_time":0.273472884,"remaining_time":9.493415831},
{"learn":[0.7197193221],"iteration":28,"passed_time":0.2840708738,"remaining_time":9.511476499},
{"learn":[0.7150262609],"iteration":29,"passed_time":0.2954816893,"remaining_time":9.553907953},
{"learn":[0.7069841769],"iteration":30,"passed_time":0.304815904,"remaining_time":9.527955192},
{"learn":[0.7000351554],"iteration":31,"passed_time":0.3138572048,"remaining_time":9.494180446},
{"learn":[0.6935936877],"iteration":32,"passed_time":0.3241651957,"remaining_time":9.499022553},
{"learn":[0.6889362539],"iteration":33,"passed_time":0.3334022649,"remaining_time":9.472546703},
{"learn":[0.6828190857],"iteration":34,"passed_time":0.3422208568,"remaining_time":9.435517909},
{"learn":[0.6786535973],"iteration":35,"passed_time":0.3516601666,"remaining_time":9.416677795},
{"learn":[0.6733953388],"iteration":36,"passed_time":0.3614338204,"remaining_time":9.407047812},
{"learn":[0.6706492447],"iteration":37,"passed_time":0.3710873621,"remaining_time":9.394369534},
{"learn":[0.6648087023],"iteration":38,"passed_time":0.3817417314,"remaining_time":9.406507791},
{"learn":[0.6594573935],"iteration":39,"passed_time":0.3907313767,"remaining_time":9.377553041},
{"learn":[0.6550520343],"iteration":40,"passed_time":0.4005229814,"remaining_time":9.368330225},
{"learn":[0.6491897616],"iteration":41,"passed_time":0.4107974511,"remaining_time":9.370094242},
{"learn":[0.6441971597],"iteration":42,"passed_time":0.4206401639,"remaining_time":9.361689229},
{"learn":[0.6396163301],"iteration":43,"passed_time":0.4306252562,"remaining_time":9.356312385},
{"learn":[0.636856752],"iteration":44,"passed_time":0.441201921,"remaining_time":9.363285213},
{"learn":[0.6319921669],"iteration":45,"passed_time":0.4517402131,"remaining_time":9.368699202},
{"learn":[0.6292705028],"iteration":46,"passed_time":0.4641188925,"remaining_time":9.41075116},
{"learn":[0.6271632904],"iteration":47,"passed_time":0.4733740318,"remaining_time":9.388584965},
{"learn":[0.623687791],"iteration":48,"passed_time":0.4849187972,"remaining_time":9.411383186},
{"learn":[0.6210721109],"iteration":49,"passed_time":0.4945039989,"remaining_time":9.39557598},
{"learn":[0.6168657274],"iteration":50,"passed_time":0.5054073021,"remaining_time":9.404539798},
{"learn":[0.6130339341],"iteration":51,"passed_time":0.5148605447,"remaining_time":9.386303777},
{"learn":[0.6082847651],"iteration":52,"passed_time":0.524633401,"remaining_time":9.374110015},
{"learn":[0.6068164119],"iteration":53,"passed_time":0.533650812,"remaining_time":9.348771632},
{"learn":[0.6037869241],"iteration":54,"passed_time":0.5431225106,"remaining_time":9.331832227},
{"learn":[0.6004895399],"iteration":55,"passed_time":0.5525186012,"remaining_time":9.313884992},
{"learn":[0.5968122672],"iteration":56,"passed_time":0.5617439967,"remaining_time":9.293413841},
{"learn":[0.5938845899],"iteration":57,"passed_time":0.5706748618,"remaining_time":9.268546894},
{"learn":[0.5921575758],"iteration":58,"passed_time":0.5799075787,"remaining_time":9.249034433},
{"learn":[0.589010129],"iteration":59,"passed_time":0.5891894704,"remaining_time":9.230635036},
{"learn":[0.5866621728],"iteration":60,"passed_time":0.6000998766,"remaining_time":9.237603019},
{"learn":[0.5833194322],"iteration":61,"passed_time":0.6092155463,"remaining_time":9.216841652},
{"learn":[0.5804754498],"iteration":62,"passed_time":0.6182063316,"remaining_time":9.194592583},
{"learn":[0.5793285994],"iteration":63,"passed_time":0.6282929293,"remaining_time":9.18878409},
{"learn":[0.576854734],"iteration":64,"passed_time":0.6389393022,"remaining_time":9.190896116},
{"learn":[0.5745489775],"iteration":65,"passed_time":0.6502978297,"remaining_time":9.202699589},
{"learn":[0.5720060399],"iteration":66,"passed_time":0.660851012,"remaining_time":9.202596928},
{"learn":[0.5695852407],"iteration":67,"passed_time":0.6705041837,"remaining_time":9.189851459},
{"learn":[0.5671577477],"iteration":68,"passed_time":0.6806667784,"remaining_time":9.184069141},
{"learn":[0.5639615431],"iteration":69,"passed_time":0.6923433579,"remaining_time":9.198276041},
{"learn":[0.5615865347],"iteration":70,"passed_time":0.7012071756,"remaining_time":9.174950227},
{"learn":[0.5581407822],"iteration":71,"passed_time":0.712151588,"remaining_time":9.178842689},
{"learn":[0.5558565769],"iteration":72,"passed_time":0.7217410113,"remaining_time":9.165122157},
{"learn":[0.5531606408],"iteration":73,"passed_time":0.7304446225,"remaining_time":9.140428655},
{"learn":[0.5510870249],"iteration":74,"passed_time":0.7402661128,"remaining_time":9.129948724},
{"learn":[0.5498394312],"iteration":75,"passed_time":0.7492804613,"remaining_time":9.109672977},
{"learn":[0.5488920089],"iteration":76,"passed_time":0.7581022381,"remaining_time":9.087381373},
{"learn":[0.5479950852],"iteration":77,"passed_time":0.7668815273,"remaining_time":9.064932925},
{"learn":[0.54624964],"iteration":78,"passed_time":0.7761563817,"remaining_time":9.048607944},
{"learn":[0.5451742882],"iteration":79,"passed_time":0.7852798619,"remaining_time":9.030718412},
{"learn":[0.5433216208],"iteration":80,"passed_time":0.794783991,"remaining_time":9.017364046},
{"learn":[0.5419156435],"iteration":81,"passed_time":0.8044610676,"remaining_time":9.006039757},
{"learn":[0.5394052151],"iteration":82,"passed_time":0.814846118,"remaining_time":9.002576991},
{"learn":[0.5379566328],"iteration":83,"passed_time":0.8254169089,"remaining_time":9.000974863},
{"learn":[0.5357243919],"iteration":84,"passed_time":0.8362246548,"remaining_time":9.001712461},
{"learn":[0.5338978952],"iteration":85,"passed_time":0.8485245638,"remaining_time":9.018040132},
{"learn":[0.5326644341],"iteration":86,"passed_time":0.8601264004,"remaining_time":9.026383949},
{"learn":[0.5315547634],"iteration":87,"passed_time":0.8714516241,"remaining_time":9.03140774},
{"learn":[0.5297158635],"iteration":88,"passed_time":0.8836242963,"remaining_time":9.044738583},
{"learn":[0.5282597183],"iteration":89,"passed_time":0.8946775096,"remaining_time":9.046183708},
{"learn":[0.5269074018],"iteration":90,"passed_time":0.904246072,"remaining_time":9.03252395},
{"learn":[0.5254595481],"iteration":91,"passed_time":0.9135568926,"remaining_time":9.016409331},
{"learn":[0.5242381182],"iteration":92,"passed_time":0.9229855453,"remaining_time":9.001590211},
{"learn":[0.5226262398],"iteration":93,"passed_time":0.9327363383,"remaining_time":8.989990665},
{"learn":[0.5212038702],"iteration":94,"passed_time":0.9420910705,"remaining_time":8.97465704},
{"learn":[0.5203096515],"iteration":95,"passed_time":0.9525960614,"remaining_time":8.970279578},
{"learn":[0.5182358682],"iteration":96,"passed_time":0.9637470726,"remaining_time":8.971789758},
{"learn":[0.5169054998],"iteration":97,"passed_time":0.9733894788,"remaining_time":8.959156223},
{"learn":[0.5152396805],"iteration":98,"passed_time":0.9831054656,"remaining_time":8.947252773},
{"learn":[0.5135573418],"iteration":99,"passed_time":0.9923281837,"remaining_time":8.930953653},
{"learn":[0.5126131174],"iteration":100,"passed_time":1.001621433,"remaining_time":8.915422461},
{"learn":[0.5107142982],"iteration":101,"passed_time":1.011246027,"remaining_time":8.902930707},
{"learn":[0.5079020239],"iteration":102,"passed_time":1.021039494,"remaining_time":8.891965303},
{"learn":[0.5067339296],"iteration":103,"passed_time":1.030370337,"remaining_time":8.877036751},
{"learn":[0.50609992],"iteration":104,"passed_time":1.040269878,"remaining_time":8.867062292},
{"learn":[0.5050542805],"iteration":105,"passed_time":1.049460056,"remaining_time":8.851106513},
{"learn":[0.5035848317],"iteration":106,"passed_time":1.062214666,"remaining_time":8.865025199},
{"learn":[0.5015189487],"iteration":107,"passed_time":1.072091887,"remaining_time":8.854684845},
{"learn":[0.5005822505],"iteration":108,"passed_time":1.081353556,"remaining_time":8.839321271},
{"learn":[0.4985201937],"iteration":109,"passed_time":1.092782562,"remaining_time":8.841604363},
{"learn":[0.4969202482],"iteration":110,"passed_time":1.103615088,"remaining_time":8.838863186},
{"learn":[0.4954509452],"iteration":111,"passed_time":1.112344721,"remaining_time":8.819304575},
{"learn":[0.4947179943],"iteration":112,"passed_time":1.121574098,"remaining_time":8.803860399},
{"learn":[0.4930497999],"iteration":113,"passed_time":1.130805295,"remaining_time":8.788539399},
{"learn":[0.4912045579],"iteration":114,"passed_time":1.139867946,"remaining_time":8.772027237},
{"learn":[0.4898642275],"iteration":115,"passed_time":1.149437408,"remaining_time":8.759505767},
{"learn":[0.4884672704],"iteration":116,"passed_time":1.1591097,"remaining_time":8.747810814},
{"learn":[0.4869339468],"iteration":117,"passed_time":1.167895025,"remaining_time":8.729520441},
{"learn":[0.4852593701],"iteration":118,"passed_time":1.177616192,"remaining_time":8.718318191},
{"learn":[0.4844858157],"iteration":119,"passed_time":1.186243537,"remaining_time":8.699119274},
{"learn":[0.482665749],"iteration":120,"passed_time":1.196097752,"remaining_time":8.689007638},
{"learn":[0.4817197847],"iteration":121,"passed_time":1.20629617,"remaining_time":8.681377353},
{"learn":[0.4804332749],"iteration":122,"passed_time":1.216628981,"remaining_time":8.67466355},
{"learn":[0.4790988418],"iteration":123,"passed_time":1.227283151,"remaining_time":8.670161613},
{"learn":[0.4772527962],"iteration":124,"passed_time":1.238758793,"remaining_time":8.67131155},
{"learn":[0.4759514944],"iteration":125,"passed_time":1.250758287,"remaining_time":8.675894782},
{"learn":[0.4748552724],"iteration":126,"passed_time":1.262122296,"remaining_time":8.675848542},
{"learn":[0.4739220026],"iteration":127,"passed_time":1.273333266,"remaining_time":8.674582876},
{"learn":[0.4729224186],"iteration":128,"passed_time":1.283055531,"remaining_time":8.663111376},
{"learn":[0.4716807602],"iteration":129,"passed_time":1.294821539,"remaining_time":8.665344144},
{"learn":[0.4708594452],"iteration":130,"passed_time":1.304829161,"remaining_time":8.655698786},
{"learn":[0.4693696043],"iteration":131,"passed_time":1.31457506,"remaining_time":8.64432691},
{"learn":[0.4680298839],"iteration":132,"passed_time":1.324571381,"remaining_time":8.634611936},
{"learn":[0.4665480068],"iteration":133,"passed_time":1.333728385,"remaining_time":8.619468519},
{"learn":[0.4654332928],"iteration":134,"passed_time":1.343356899,"remaining_time":8.607434948},
{"learn":[0.4644471689],"iteration":135,"passed_time":1.353262589,"remaining_time":8.597197624},
{"learn":[0.463397022],"iteration":136,"passed_time":1.362823638,"remaining_time":8.58479416},
{"learn":[0.4624165968],"iteration":137,"passed_time":1.372048868,"remaining_time":8.570334234},
{"learn":[0.4614345269],"iteration":138,"passed_time":1.38129468,"remaining_time":8.55607712},
{"learn":[0.4602749908],"iteration":139,"passed_time":1.390462586,"remaining_time":8.54141303},
{"learn":[0.459091958],"iteration":140,"passed_time":1.399409239,"remaining_time":8.525478981},
{"learn":[0.458292969],"iteration":141,"passed_time":1.409248746,"remaining_time":8.515038199},
{"learn":[0.4571202061],"iteration":142,"passed_time":1.419180766,"remaining_time":8.505160257},
{"learn":[0.4559425538],"iteration":143,"passed_time":1.429486769,"remaining_time":8.497504682},
{"learn":[0.455396448],"iteration":144,"passed_time":1.439517362,"remaining_time":8.488188584},
{"learn":[0.4540043985],"iteration":145,"passed_time":1.450249029,"remaining_time":8.4829635},
{"learn":[0.4522801284],"iteration":146,"passed_time":1.463984371,"remaining_time":8.495092983},
{"learn":[0.4516057926],"iteration":147,"passed_time":1.474916681,"remaining_time":8.490736572},
{"learn":[0.4502149851],"iteration":148,"passed_time":1.487776733,"remaining_time":8.497302014},
{"learn":[0.4489767602],"iteration":149,"passed_time":1.498155821,"remaining_time":8.489549655},
{"learn":[0.4479281616],"iteration":150,"passed_time":1.509820407,"remaining_time":8.488990237},
{"learn":[0.4466369615],"iteration":151,"passed_time":1.522404028,"remaining_time":8.493411945},
{"learn":[0.4451963755],"iteration":152,"passed_time":1.533555997,"remaining_time":8.489685816},
{"learn":[0.444122485],"iteration":153,"passed_time":1.545189438,"remaining_time":8.48850821},
{"learn":[0.4430300293],"iteration":154,"passed_time":1.556719839,"remaining_time":8.486633959},
{"learn":[0.4417984065],"iteration":155,"passed_time":1.56920087,"remaining_time":8.489779065},
{"learn":[0.4409005897],"iteration":156,"passed_time":1.578933504,"remaining_time":8.477967797},
{"learn":[0.4394047962],"iteration":157,"passed_time":1.588063952,"remaining_time":8.462973718},
{"learn":[0.4381830975],"iteration":158,"passed_time":1.597370568,"remaining_time":8.448985208},
{"learn":[0.437657684],"iteration":159,"passed_time":1.60622116,"remaining_time":8.432661089},
{"learn":[0.4373464296],"iteration":160,"passed_time":1.615612993,"remaining_time":8.419250319},
{"learn":[0.4361717565],"iteration":161,"passed_time":1.625454949,"remaining_time":8.408217578},
{"learn":[0.4353206539],"iteration":162,"passed_time":1.635492248,"remaining_time":8.398202525},
{"learn":[0.4341184095],"iteration":163,"passed_time":1.645431251,"remaining_time":8.387686131},
{"learn":[0.4329804254],"iteration":164,"passed_time":1.656577082,"remaining_time":8.383284021},
{"learn":[0.4319872688],"iteration":165,"passed_time":1.666426527,"remaining_time":8.372287491},
{"learn":[0.4304783468],"iteration":166,"passed_time":1.677754636,"remaining_time":8.368680308},
{"learn":[0.4298103246],"iteration":167,"passed_time":1.686465773,"remaining_time":8.352020972},
{"learn":[0.4282990358],"iteration":168,"passed_time":1.697216495,"remaining_time":8.345484657},
{"learn":[0.4277996922],"iteration":169,"passed_time":1.707707636,"remaining_time":8.337631399},
{"learn":[0.4270518593],"iteration":170,"passed_time":1.717023433,"remaining_time":8.324049275},
{"learn":[0.4259059826],"iteration":171,"passed_time":1.727510849,"remaining_time":8.316156877},
{"learn":[0.4249464523],"iteration":172,"passed_time":1.740172048,"remaining_time":8.318625918},
{"learn":[0.4239709528],"iteration":173,"passed_time":1.749695931,"remaining_time":8.306027813},
{"learn":[0.4233271891],"iteration":174,"passed_time":1.759402836,"remaining_time":8.294327656},
{"learn":[0.4225112534],"iteration":175,"passed_time":1.768330374,"remaining_time":8.279001296},
{"learn":[0.4213808247],"iteration":176,"passed_time":1.778036197,"remaining_time":8.267366045},
{"learn":[0.4207315977],"iteration":177,"passed_time":1.787442435,"remaining_time":8.254369},
{"learn":[0.4202909513],"iteration":178,"passed_time":1.796521417,"remaining_time":8.239911082},
{"learn":[0.4192841414],"iteration":179,"passed_time":1.805649127,"remaining_time":8.225734914},
{"learn":[0.4182173423],"iteration":180,"passed_time":1.816296415,"remaining_time":8.218490406},
{"learn":[0.4174631154],"iteration":181,"passed_time":1.825390672,"remaining_time":8.204228403},
{"learn":[0.4169160476],"iteration":182,"passed_time":1.834991758,"remaining_time":8.192285607},
{"learn":[0.4159626042],"iteration":183,"passed_time":1.846159834,"remaining_time":8.187317526},
{"learn":[0.4152317609],"iteration":184,"passed_time":1.858804901,"remaining_time":8.188789158},
{"learn":[0.4145206968],"iteration":185,"passed_time":1.869005984,"remaining_time":8.179413286},
{"learn":[0.4132505054],"iteration":186,"passed_time":1.879134008,"remaining_time":8.169710954},
{"learn":[0.4124287125],"iteration":187,"passed_time":1.890738936,"remaining_time":8.166383063},
{"learn":[0.4116121842],"iteration":188,"passed_time":1.901661182,"remaining_time":8.160038195},
{"learn":[0.4108841278],"iteration":189,"passed_time":1.912222582,"remaining_time":8.152106797},
{"learn":[0.4101696609],"iteration":190,"passed_time":1.922181221,"remaining_time":8.141594806},
{"learn":[0.4091488543],"iteration":191,"passed_time":1.931591293,"remaining_time":8.128780024},
{"learn":[0.4083539622],"iteration":192,"passed_time":1.940802504,"remaining_time":8.115169019},
{"learn":[0.4076402284],"iteration":193,"passed_time":1.95113397,"remaining_time":8.106257627},
{"learn":[0.4067481189],"iteration":194,"passed_time":1.961997276,"remaining_time":8.099527217},
{"learn":[0.4059627859],"iteration":195,"passed_time":1.971911518,"remaining_time":8.088861532},
{"learn":[0.4048023828],"iteration":196,"passed_time":1.982635052,"remaining_time":8.081502268},
{"learn":[0.404045618],"iteration":197,"passed_time":1.992345404,"remaining_time":8.070005121},
{"learn":[0.4029013664],"iteration":198,"passed_time":2.00328528,"remaining_time":8.063474921},
{"learn":[0.40212457],"iteration":199,"passed_time":2.012513935,"remaining_time":8.050055738},
{"learn":[0.4014708781],"iteration":200,"passed_time":2.023354549,"remaining_time":8.043085994},
{"learn":[0.4006507362],"iteration":201,"passed_time":2.034281901,"remaining_time":8.036420581},
{"learn":[0.4001689645],"iteration":202,"passed_time":2.04390826,"remaining_time":8.024605336},
{"learn":[0.3997934917],"iteration":203,"passed_time":2.055124389,"remaining_time":8.019014772},
{"learn":[0.3985112537],"iteration":204,"passed_time":2.068090844,"remaining_time":8.020157176},
{"learn":[0.3980730704],"iteration":205,"passed_time":2.077116567,"remaining_time":8.005973565},
{"learn":[0.3972700302],"iteration":206,"passed_time":2.086363803,"remaining_time":7.992688387},
{"learn":[0.3963462327],"iteration":207,"passed_time":2.096474218,"remaining_time":7.982728752},
{"learn":[0.3956390642],"iteration":208,"passed_time":2.107080508,"remaining_time":7.974644411},
{"learn":[0.3952646917],"iteration":209,"passed_time":2.115959643,"remaining_time":7.960038659},
{"learn":[0.3944670311],"iteration":210,"passed_time":2.125751711,"remaining_time":7.948900946},
{"learn":[0.3936090167],"iteration":211,"passed_time":2.135063138,"remaining_time":7.935989399},
{"learn":[0.392990444],"iteration":212,"passed_time":2.145372338,"remaining_time":7.926798262},
{"learn":[0.3921657801],"iteration":213,"passed_time":2.154509863,"remaining_time":7.913293233},
{"learn":[0.3914487099],"iteration":214,"passed_time":2.163581854,"remaining_time":7.89958956},
{"learn":[0.3905839321],"iteration":215,"passed_time":2.173566015,"remaining_time":7.889239609},
{"learn":[0.3900091159],"iteration":216,"passed_time":2.182980346,"remaining_time":7.876836918},
{"learn":[0.3895507168],"iteration":217,"passed_time":2.191684979,"remaining_time":7.861915843},
{"learn":[0.3889630402],"iteration":218,"passed_time":2.200879967,"remaining_time":7.848800249},
{"learn":[0.3884178252],"iteration":219,"passed_time":2.210209611,"remaining_time":7.836197713},
{"learn":[0.3873977936],"iteration":220,"passed_time":2.220062332,"remaining_time":7.825468583},
{"learn":[0.3869878233],"iteration":221,"passed_time":2.228891392,"remaining_time":7.811159923},
{"learn":[0.3864215291],"iteration":222,"passed_time":2.23919274,"remaining_time":7.802030309},
{"learn":[0.3858898784],"iteration":223,"passed_time":2.248992443,"remaining_time":7.791152393},
{"learn":[0.3853970618],"iteration":224,"passed_time":2.260589623,"remaining_time":7.78647537},
{"learn":[0.3838382581],"iteration":225,"passed_time":2.270495955,"remaining_time":7.775946325},
{"learn":[0.3829579345],"iteration":226,"passed_time":2.280244314,"remaining_time":7.764884824},
{"learn":[0.3824399666],"iteration":227,"passed_time":2.290988466,"remaining_time":7.75720656},
{"learn":[0.3819196984],"iteration":228,"passed_time":2.301653793,"remaining_time":7.749236134},
{"learn":[0.381103112],"iteration":229,"passed_time":2.311127902,"remaining_time":7.73725428},
{"learn":[0.3806617896],"iteration":230,"passed_time":2.32038858,"remaining_time":7.724583628},
{"learn":[0.3802879175],"iteration":231,"passed_time":2.329725302,"remaining_time":7.712194104},
{"learn":[0.3798237117],"iteration":232,"passed_time":2.339356523,"remaining_time":7.700800228},
{"learn":[0.3792851093],"iteration":233,"passed_time":2.348331756,"remaining_time":7.68727404},
{"learn":[0.377910775],"iteration":234,"passed_time":2.357550436,"remaining_time":7.674579077},
{"learn":[0.3777737513],"iteration":235,"passed_time":2.366858642,"remaining_time":7.662203401},
{"learn":[0.3769233898],"iteration":236,"passed_time":2.376152099,"remaining_time":7.649806125},
{"learn":[0.3759304005],"iteration":237,"passed_time":2.386029201,"remaining_time":7.639303575},
{"learn":[0.3753358088],"iteration":238,"passed_time":2.395133175,"remaining_time":7.626344544},
{"learn":[0.3747647613],"iteration":239,"passed_time":2.405278196,"remaining_time":7.616714288},
{"learn":[0.374316184],"iteration":240,"passed_time":2.415596645,"remaining_time":7.607625948},
{"learn":[0.3733865562],"iteration":241,"passed_time":2.4254389,"remaining_time":7.597035894},
{"learn":[0.3729292174],"iteration":242,"passed_time":2.435243705,"remaining_time":7.586335329},
{"learn":[0.3726252801],"iteration":243,"passed_time":2.445216721,"remaining_time":7.576163282},
{"learn":[0.3719838969],"iteration":244,"passed_time":2.458347468,"remaining_time":7.57572383},
{"learn":[0.3715556249],"iteration":245,"passed_time":2.467426203,"remaining_time":7.562761615},
{"learn":[0.3712112509],"iteration":246,"passed_time":2.478575728,"remaining_time":7.556143818},
{"learn":[0.3702991623],"iteration":247,"passed_time":2.490604088,"remaining_time":7.552154332},
{"learn":[0.3699520193],"iteration":248,"passed_time":2.501513948,"remaining_time":7.544726806},
{"learn":[0.3692680613],"iteration":249,"passed_time":2.51132479,"remaining_time":7.53397437},
{"learn":[0.3688893062],"iteration":250,"passed_time":2.52095091,"remaining_time":7.522678214},
{"learn":[0.3683420147],"iteration":251,"passed_time":2.529992534,"remaining_time":7.509660377},
{"learn":[0.3679964773],"iteration":252,"passed_time":2.53905374,"remaining_time":7.496731795},
{"learn":[0.367433622],"iteration":253,"passed_time":2.5489003,"remaining_time":7.48614025},
{"learn":[0.366717364],"iteration":254,"passed_time":2.558725444,"remaining_time":7.475491983},
{"learn":[0.3659902288],"iteration":255,"passed_time":2.568056726,"remaining_time":7.463414861},
{"learn":[0.3654878383],"iteration":256,"passed_time":2.577721223,"remaining_time":7.452322447},
{"learn":[0.3650349743],"iteration":257,"passed_time":2.587576424,"remaining_time":7.44178956},
{"learn":[0.3642976768],"iteration":258,"passed_time":2.596632138,"remaining_time":7.428974571},
{"learn":[0.3639434547],"iteration":259,"passed_time":2.606559239,"remaining_time":7.418668603},
{"learn":[0.3632954969],"iteration":260,"passed_time":2.616635689,"remaining_time":7.408788405},
{"learn":[0.3623957763],"iteration":261,"passed_time":2.62623473,"remaining_time":7.397561949},
{"learn":[0.3619128695],"iteration":262,"passed_time":2.637275634,"remaining_time":7.390388375},
{"learn":[0.3615730094],"iteration":263,"passed_time":2.647662243,"remaining_time":7.381361405},
{"learn":[0.361123923],"iteration":264,"passed_time":2.657463922,"remaining_time":7.37070182},
{"learn":[0.360651899],"iteration":265,"passed_time":2.669270733,"remaining_time":7.365581646},
{"learn":[0.3601475672],"iteration":266,"passed_time":2.680498129,"remaining_time":7.358820707},
{"learn":[0.3595271661],"iteration":267,"passed_time":2.69036483,"remaining_time":7.348309908},
{"learn":[0.3588046976],"iteration":268,"passed_time":2.702435314,"remaining_time":7.343792619},
{"learn":[0.358147825],"iteration":269,"passed_time":2.711689602,"remaining_time":7.33160522},
{"learn":[0.3574956816],"iteration":270,"passed_time":2.721441245,"remaining_time":7.32077737},
{"learn":[0.3571545722],"iteration":271,"passed_time":2.730654788,"remaining_time":7.308517227},
{"learn":[0.3567953479],"iteration":272,"passed_time":2.739754643,"remaining_time":7.295976651},
{"learn":[0.3561352775],"iteration":273,"passed_time":2.749475725,"remaining_time":7.285107213},
{"learn":[0.3558146507],"iteration":274,"passed_time":2.759589374,"remaining_time":7.275281077},
{"learn":[0.3555575651],"iteration":275,"passed_time":2.768506909,"remaining_time":7.262315225},
{"learn":[0.3550719202],"iteration":276,"passed_time":2.777872628,"remaining_time":7.250548412},
{"learn":[0.3543369439],"iteration":277,"passed_time":2.787451358,"remaining_time":7.239352087},
{"learn":[0.3537932619],"iteration":278,"passed_time":2.796242141,"remaining_time":7.226131123},
{"learn":[0.3533123777],"iteration":279,"passed_time":2.805777338,"remaining_time":7.214856011},
{"learn":[0.3526761126],"iteration":280,"passed_time":2.81540211,"remaining_time":7.203822482},
{"learn":[0.3521051587],"iteration":281,"passed_time":2.824951861,"remaining_time":7.19260793},
{"learn":[0.3516104209],"iteration":282,"passed_time":2.834513504,"remaining_time":7.181435273},
{"learn":[0.3513356729],"iteration":283,"passed_time":2.844274408,"remaining_time":7.170776324},
{"learn":[0.3510487841],"iteration":284,"passed_time":2.856535552,"remaining_time":7.166396209},
{"learn":[0.3506947759],"iteration":285,"passed_time":2.867427289,"remaining_time":7.158542252},
{"learn":[0.3502067305],"iteration":286,"passed_time":2.876770852,"remaining_time":7.146820968},
{"learn":[0.3499548633],"iteration":287,"passed_time":2.885622566,"remaining_time":7.133900233},
{"learn":[0.3495277809],"iteration":288,"passed_time":2.898476381,"remaining_time":7.130853657},
{"learn":[0.3490342358],"iteration":289,"passed_time":2.907908382,"remaining_time":7.1193619},
{"learn":[0.3485246888],"iteration":290,"passed_time":2.917938071,"remaining_time":7.109340523},
{"learn":[0.3477443711],"iteration":291,"passed_time":2.927273404,"remaining_time":7.097635513},
{"learn":[0.3469905295],"iteration":292,"passed_time":2.936881665,"remaining_time":7.086605247},
{"learn":[0.3463669287],"iteration":293,"passed_time":2.946887242,"remaining_time":7.076538751},
{"learn":[0.3458660301],"iteration":294,"passed_time":2.957666923,"remaining_time":7.068322647},
{"learn":[0.3457517317],"iteration":295,"passed_time":2.967257105,"remaining_time":7.057260141},
{"learn":[0.3453251622],"iteration":296,"passed_time":2.976705439,"remaining_time":7.045871797},
{"learn":[0.3445590379],"iteration":297,"passed_time":2.986068657,"remaining_time":7.034295964},
{"learn":[0.3437300854],"iteration":298,"passed_time":2.995325779,"remaining_time":7.022486191},
{"learn":[0.3432064613],"iteration":299,"passed_time":3.005014651,"remaining_time":7.011700852},
{"learn":[0.3425662528],"iteration":300,"passed_time":3.014531989,"remaining_time":7.000524454},
{"learn":[0.3422938746],"iteration":301,"passed_time":3.024444809,"remaining_time":6.990273103},
{"learn":[0.3420728816],"iteration":302,"passed_time":3.033571958,"remaining_time":6.978216682},
{"learn":[0.3415796967],"iteration":303,"passed_time":3.044558203,"remaining_time":6.970435886},
{"learn":[0.3411928944],"iteration":304,"passed_time":3.058496008,"remaining_time":6.969359755},
{"learn":[0.3407502767],"iteration":305,"passed_time":3.072763174,"remaining_time":6.968946545},
{"learn":[0.3402863479],"iteration":306,"passed_time":3.082237099,"remaining_time":6.957623159},
{"learn":[0.3399881081],"iteration":307,"passed_time":3.092161126,"remaining_time":6.947323049},
{"learn":[0.3393361537],"iteration":308,"passed_time":3.103965817,"remaining_time":6.941231002},
{"learn":[0.3388741728],"iteration":309,"passed_time":3.114914906,"remaining_time":6.933197694},
{"learn":[0.3382304383],"iteration":310,"passed_time":3.126016011,"remaining_time":6.925482416},
{"learn":[0.33756172],"iteration":311,"passed_time":3.13593915,"remaining_time":6.915147868},
{"learn":[0.3371837201],"iteration":312,"passed_time":3.145989326,"remaining_time":6.905094783},
{"learn":[0.3369909881],"iteration":313,"passed_time":3.156474181,"remaining_time":6.895991364},
{"learn":[0.3366588092],"iteration":314,"passed_time":3.166745063,"remaining_time":6.886413868},
{"learn":[0.336245197],"iteration":315,"passed_time":3.177434433,"remaining_time":6.877737823},
{"learn":[0.3360412427],"iteration":316,"passed_time":3.18713285,"remaining_time":6.866913995},
{"learn":[0.33567646],"iteration":317,"passed_time":3.196669151,"remaining_time":6.855749562},
{"learn":[0.3352961476],"iteration":318,"passed_time":3.209125114,"remaining_time":6.850828221},
{"learn":[0.3350529895],"iteration":319,"passed_time":3.218923961,"remaining_time":6.840213417},
{"learn":[0.3348118694],"iteration":320,"passed_time":3.229263926,"remaining_time":6.830748305},
{"learn":[0.3344112347],"iteration":321,"passed_time":3.241393523,"remaining_time":6.825045989},
{"learn":[0.3339384598],"iteration":322,"passed_time":3.254567786,"remaining_time":6.821493471},
{"learn":[0.3337334098],"iteration":323,"passed_time":3.26414283,"remaining_time":6.810372077},
{"learn":[0.3334137194],"iteration":324,"passed_time":3.275902039,"remaining_time":6.803796543},
{"learn":[0.3331053112],"iteration":325,"passed_time":3.286112852,"remaining_time":6.793987921},
{"learn":[0.3327311887],"iteration":326,"passed_time":3.295698606,"remaining_time":6.782890402},
{"learn":[0.3323254207],"iteration":327,"passed_time":3.30580617,"remaining_time":6.772871178},
{"learn":[0.332067664],"iteration":328,"passed_time":3.315159967,"remaining_time":6.761314097},
{"learn":[0.3317491517],"iteration":329,"passed_time":3.324287616,"remaining_time":6.74931122},
{"learn":[0.3312169041],"iteration":330,"passed_time":3.33316101,"remaining_time":6.736811831},
{"learn":[0.3306826837],"iteration":331,"passed_time":3.343088943,"remaining_time":6.726456067},
{"learn":[0.3303256855],"iteration":332,"passed_time":3.352304176,"remaining_time":6.714675331},
{"learn":[0.3298841523],"iteration":333,"passed_time":3.36116029,"remaining_time":6.702193871},
{"learn":[0.3293426026],"iteration":334,"passed_time":3.370356192,"remaining_time":6.69040856},
{"learn":[0.328789052],"iteration":335,"passed_time":3.378921583,"remaining_time":6.677392652},
{"learn":[0.3284805608],"iteration":336,"passed_time":3.388164162,"remaining_time":6.665735428},
{"learn":[0.3280764204],"iteration":337,"passed_time":3.397170307,"remaining_time":6.653629419},
{"learn":[0.3277099665],"iteration":338,"passed_time":3.40627659,"remaining_time":6.64173695},
{"learn":[0.327402896],"iteration":339,"passed_time":3.41713839,"remaining_time":6.63326864},
{"learn":[0.326972884],"iteration":340,"passed_time":3.426812456,"remaining_time":6.622490935},
{"learn":[0.3267454871],"iteration":341,"passed_time":3.436932517,"remaining_time":6.612577766},
{"learn":[0.3263480798],"iteration":342,"passed_time":3.447923956,"remaining_time":6.604332475},
{"learn":[0.3259136308],"iteration":343,"passed_time":3.459857546,"remaining_time":6.597867878},
{"learn":[0.3255533115],"iteration":344,"passed_time":3.470166565,"remaining_time":6.588287246},
{"learn":[0.3248878224],"iteration":345,"passed_time":3.480562986,"remaining_time":6.578867608},
{"learn":[0.3242367982],"iteration":346,"passed_time":3.490766002,"remaining_time":6.569078384},
{"learn":[0.3239024627],"iteration":347,"passed_time":3.500442399,"remaining_time":6.558300126},
{"learn":[0.3235978071],"iteration":348,"passed_time":3.512385451,"remaining_time":6.551756241},
{"learn":[0.3232162904],"iteration":349,"passed_time":3.521948706,"remaining_time":6.540761883},
{"learn":[0.3227085634],"iteration":350,"passed_time":3.531992584,"remaining_time":6.530664351},
{"learn":[0.322244799],"iteration":351,"passed_time":3.541077698,"remaining_time":6.518802126},
{"learn":[0.3218346306],"iteration":352,"passed_time":3.550256596,"remaining_time":6.507127529},
{"learn":[0.321392275],"iteration":353,"passed_time":3.55898579,"remaining_time":6.494646385},
{"learn":[0.3211781195],"iteration":354,"passed_time":3.56812208,"remaining_time":6.482926032},
{"learn":[0.3208416482],"iteration":355,"passed_time":3.577173046,"remaining_time":6.471065847},
{"learn":[0.3206444319],"iteration":356,"passed_time":3.586470499,"remaining_time":6.459665352},
{"learn":[0.3204474802],"iteration":357,"passed_time":3.595909183,"remaining_time":6.448529875},
{"learn":[0.3201531719],"iteration":358,"passed_time":3.604739537,"remaining_time":6.436317669},
{"learn":[0.3198088784],"iteration":359,"passed_time":3.613815885,"remaining_time":6.424561573},
{"learn":[0.3195707399],"iteration":360,"passed_time":3.62309652,"remaining_time":6.413181928},
{"learn":[0.3193419828],"iteration":361,"passed_time":3.632433188,"remaining_time":6.401912635},
{"learn":[0.3190852837],"iteration":362,"passed_time":3.642354916,"remaining_time":6.391680665},
{"learn":[0.318602592],"iteration":363,"passed_time":3.654233373,"remaining_time":6.384869301},
{"learn":[0.3183378233],"iteration":364,"passed_time":3.669320652,"remaining_time":6.383612641},
{"learn":[0.3180728703],"iteration":365,"passed_time":3.679474538,"remaining_time":6.373734582},
{"learn":[0.3175859744],"iteration":366,"passed_time":3.690482196,"remaining_time":6.365327603},
{"learn":[0.3170912961],"iteration":367,"passed_time":3.701575479,"remaining_time":6.357053539},
{"learn":[0.3165724344],"iteration":368,"passed_time":3.711428069,"remaining_time":6.346642579},
{"learn":[0.316255479],"iteration":369,"passed_time":3.720899121,"remaining_time":6.33558499},
{"learn":[0.3160444667],"iteration":370,"passed_time":3.732074328,"remaining_time":6.327425209},
{"learn":[0.3158398281],"iteration":371,"passed_time":3.742280586,"remaining_time":6.317613462},
{"learn":[0.3155384066],"iteration":372,"passed_time":3.752409782,"remaining_time":6.307670062},
{"learn":[0.3151853626],"iteration":373,"passed_time":3.763168909,"remaining_time":6.298780045},
{"learn":[0.3146751441],"iteration":374,"passed_time":3.773674099,"remaining_time":6.289456831},
{"learn":[0.3143375044],"iteration":375,"passed_time":3.783674615,"remaining_time":6.279289786},
{"learn":[0.3139066678],"iteration":376,"passed_time":3.792925107,"remaining_time":6.267884196},
{"learn":[0.3136547662],"iteration":377,"passed_time":3.802532882,"remaining_time":6.257077916},
{"learn":[0.3131301582],"iteration":378,"passed_time":3.813026207,"remaining_time":6.247728957},
{"learn":[0.312729162],"iteration":379,"passed_time":3.822743406,"remaining_time":6.237107662},
{"learn":[0.3125691059],"iteration":380,"passed_time":3.832381446,"remaining_time":6.226362507},
{"learn":[0.312180924],"iteration":381,"passed_time":3.843046103,"remaining_time":6.21728401},
{"learn":[0.311560212],"iteration":382,"passed_time":3.856646569,"remaining_time":6.212926718},
{"learn":[0.3113087204],"iteration":383,"passed_time":3.866148251,"remaining_time":6.201946153},
{"learn":[0.3108507969],"iteration":384,"passed_time":3.878489492,"remaining_time":6.195509188},
{"learn":[0.3104553691],"iteration":385,"passed_time":3.890625762,"remaining_time":6.188715591},
{"learn":[0.3102007632],"iteration":386,"passed_time":3.900623514,"remaining_time":6.178507013},
{"learn":[0.3097706677],"iteration":387,"passed_time":3.910166928,"remaining_time":6.167582887},
{"learn":[0.3092768384],"iteration":388,"passed_time":3.919343616,"remaining_time":6.156089843},
{"learn":[0.3088385246],"iteration":389,"passed_time":3.928683802,"remaining_time":6.144864408},
{"learn":[0.3085050332],"iteration":390,"passed_time":3.938073212,"remaining_time":6.133725284},
{"learn":[0.3079706724],"iteration":391,"passed_time":3.946875375,"remaining_time":6.121684255},
{"learn":[0.3077612696],"iteration":392,"passed_time":3.956076317,"remaining_time":6.110275634},
{"learn":[0.3074653072],"iteration":393,"passed_time":3.964743525,"remaining_time":6.0980573},
{"learn":[0.3072964758],"iteration":394,"passed_time":3.974042878,"remaining_time":6.086825167},
{"learn":[0.3069763497],"iteration":395,"passed_time":3.984474396,"remaining_time":6.077329634},
{"learn":[0.3062772565],"iteration":396,"passed_time":3.993823321,"remaining_time":6.066185045},
{"learn":[0.3059829078],"iteration":397,"passed_time":4.003697107,"remaining_time":6.055843363},
{"learn":[0.3057801079],"iteration":398,"passed_time":4.013299383,"remaining_time":6.045095061},
{"learn":[0.3054007492],"iteration":399,"passed_time":4.023267835,"remaining_time":6.034901752},
{"learn":[0.3051911266],"iteration":400,"passed_time":4.032371453,"remaining_time":6.023417707},
{"learn":[0.3047637174],"iteration":401,"passed_time":4.042484818,"remaining_time":6.013447565},
{"learn":[0.3041412238],"iteration":402,"passed_time":4.053098688,"remaining_time":6.004218156},
{"learn":[0.303937235],"iteration":403,"passed_time":4.063519696,"remaining_time":5.994697374},
{"learn":[0.303718144],"iteration":404,"passed_time":4.074147112,"remaining_time":5.985475387},
{"learn":[0.3033410696],"iteration":405,"passed_time":4.083099784,"remaining_time":5.973796236},
{"learn":[0.3032234526],"iteration":406,"passed_time":4.094049419,"remaining_time":5.965040062},
{"learn":[0.3029355998],"iteration":407,"passed_time":4.103552539,"remaining_time":5.954174272},
{"learn":[0.3024032177],"iteration":408,"passed_time":4.113104122,"remaining_time":5.943385174},
{"learn":[0.302326674],"iteration":409,"passed_time":4.121931398,"remaining_time":5.931559816},
{"learn":[0.3019711113],"iteration":410,"passed_time":4.132009956,"remaining_time":5.921542249},
{"learn":[0.3018146558],"iteration":411,"passed_time":4.141247813,"remaining_time":5.910324549},
{"learn":[0.3013654294],"iteration":412,"passed_time":4.150416451,"remaining_time":5.899018055},
{"learn":[0.3009517763],"iteration":413,"passed_time":4.160218021,"remaining_time":5.888617778},
{"learn":[0.3006453062],"iteration":414,"passed_time":4.169894609,"remaining_time":5.878044208},
{"learn":[0.3002983507],"iteration":415,"passed_time":4.178519186,"remaining_time":5.865998088},
{"learn":[0.3001231565],"iteration":416,"passed_time":4.18867132,"remaining_time":5.856104028},
{"learn":[0.2999496443],"iteration":417,"passed_time":4.198644235,"remaining_time":5.845959198},
{"learn":[0.2998424368],"iteration":418,"passed_time":4.207877347,"remaining_time":5.834789353},
{"learn":[0.2992906037],"iteration":419,"passed_time":4.217830962,"remaining_time":5.824623709},
{"learn":[0.2990102696],"iteration":420,"passed_time":4.227526059,"remaining_time":5.814103534},
{"learn":[0.2987031136],"iteration":421,"passed_time":4.237709008,"remaining_time":5.804255465},
{"learn":[0.2984362365],"iteration":422,"passed_time":4.248404447,"remaining_time":5.795104884},
{"learn":[0.2982558234],"iteration":423,"passed_time":4.261162099,"remaining_time":5.788748511},
{"learn":[0.2979489207],"iteration":424,"passed_time":4.272521913,"remaining_time":5.780470823},
{"learn":[0.2977597216],"iteration":425,"passed_time":4.283767555,"remaining_time":5.772024828},
{"learn":[0.2976170478],"iteration":426,"passed_time":4.293679825,"remaining_time":5.76177644},
{"learn":[0.297075424],"iteration":427,"passed_time":4.30337702,"remaining_time":5.751242186},
{"learn":[0.2968527513],"iteration":428,"passed_time":4.313653759,"remaining_time":5.741483208},
{"learn":[0.2967303683],"iteration":429,"passed_time":4.3229232,"remaining_time":5.730386567},
{"learn":[0.2963698451],"iteration":430,"passed_time":4.332058786,"remaining_time":5.719121692},
{"learn":[0.2961822861],"iteration":431,"passed_time":4.341207174,"remaining_time":5.707883507},
{"learn":[0.296110784],"iteration":432,"passed_time":4.35154389,"remaining_time":5.698211052},
{"learn":[0.2956459089],"iteration":433,"passed_time":4.361212769,"remaining_time":5.68766458},
{"learn":[0.2950890588],"iteration":434,"passed_time":4.37046411,"remaining_time":5.676579821},
{"learn":[0.2948109168],"iteration":435,"passed_time":4.379841517,"remaining_time":5.66566655},
{"learn":[0.2945029837],"iteration":436,"passed_time":4.388829121,"remaining_time":5.654258112},
{"learn":[0.2941590522],"iteration":437,"passed_time":4.398145547,"remaining_time":5.643282642},
{"learn":[0.2939102061],"iteration":438,"passed_time":4.407802718,"remaining_time":5.63275017},
{"learn":[0.2936106273],"iteration":439,"passed_time":4.416663278,"remaining_time":5.621207808},
{"learn":[0.2934943855],"iteration":440,"passed_time":4.426285096,"remaining_time":5.610642559},
{"learn":[0.2931693354],"iteration":441,"passed_time":4.435159421,"remaining_time":5.599137912},
{"learn":[0.2929414801],"iteration":442,"passed_time":4.44564363,"remaining_time":5.589669304},
{"learn":[0.2926783412],"iteration":443,"passed_time":4.456283205,"remaining_time":5.58039068},
{"learn":[0.2924869911],"iteration":444,"passed_time":4.467149472,"remaining_time":5.571388667},
{"learn":[0.2920673374],"iteration":445,"passed_time":4.478834742,"remaining_time":5.563395622},
{"learn":[0.2918472619],"iteration":446,"passed_time":4.48771219,"remaining_time":5.551912397},
{"learn":[0.2916768388],"iteration":447,"passed_time":4.497345769,"remaining_time":5.541372465},
{"learn":[0.291356977],"iteration":448,"passed_time":4.508363706,"remaining_time":5.532535416},
{"learn":[0.2907905601],"iteration":449,"passed_time":4.517455265,"remaining_time":5.521334212},
{"learn":[0.290500359],"iteration":450,"passed_time":4.527528864,"remaining_time":5.511337796},
{"learn":[0.2902274293],"iteration":451,"passed_time":4.537442206,"remaining_time":5.501146746},
{"learn":[0.2901228078],"iteration":452,"passed_time":4.546262156,"remaining_time":5.489636643},
{"learn":[0.289663536],"iteration":453,"passed_time":4.555669187,"remaining_time":5.47884444},
{"learn":[0.2893599178],"iteration":454,"passed_time":4.56439385,"remaining_time":5.467240986},
{"learn":[0.288961492],"iteration":455,"passed_time":4.573549044,"remaining_time":5.456163772},
{"learn":[0.2886823702],"iteration":456,"passed_time":4.582758365,"remaining_time":5.445159282},
{"learn":[0.2886386224],"iteration":457,"passed_time":4.591331431,"remaining_time":5.433409685},
{"learn":[0.2885732418],"iteration":458,"passed_time":4.600157818,"remaining_time":5.421972505},
{"learn":[0.288160089],"iteration":459,"passed_time":4.610028259,"remaining_time":5.411772304},
{"learn":[0.2879087997],"iteration":460,"passed_time":4.620964017,"remaining_time":5.4028191},
{"learn":[0.2877221077],"iteration":461,"passed_time":4.630001203,"remaining_time":5.391646423},
{"learn":[0.2871309115],"iteration":462,"passed_time":4.640737734,"remaining_time":5.382453916},
{"learn":[0.2868185402],"iteration":463,"passed_time":4.652043964,"remaining_time":5.373912855},
{"learn":[0.2864794064],"iteration":464,"passed_time":4.664493322,"remaining_time":5.366675112},
{"learn":[0.2859718888],"iteration":465,"passed_time":4.676686556,"remaining_time":5.359121504},
{"learn":[0.2854515377],"iteration":466,"passed_time":4.686349173,"remaining_time":5.348659763},
{"learn":[0.2852228077],"iteration":467,"passed_time":4.696381769,"remaining_time":5.338622011},
{"learn":[0.2850279935],"iteration":468,"passed_time":4.706930639,"remaining_time":5.329168805},
{"learn":[0.2847459244],"iteration":469,"passed_time":4.717403769,"remaining_time":5.319625527},
{"learn":[0.2845809475],"iteration":470,"passed_time":4.726286996,"remaining_time":5.308292613},
{"learn":[0.2843148004],"iteration":471,"passed_time":4.735545376,"remaining_time":5.297389743},
{"learn":[0.2841931049],"iteration":472,"passed_time":4.745355063,"remaining_time":5.287108073},
{"learn":[0.2839671384],"iteration":473,"passed_time":4.754564275,"remaining_time":5.276162043},
{"learn":[0.2837104923],"iteration":474,"passed_time":4.763877973,"remaining_time":5.265338813},
{"learn":[0.2834457784],"iteration":475,"passed_time":4.773690985,"remaining_time":5.255071588},
{"learn":[0.283281487],"iteration":476,"passed_time":4.783876823,"remaining_time":5.245215049},
{"learn":[0.2828891102],"iteration":477,"passed_time":4.79294037,"remaining_time":5.234131534},
{"learn":[0.282660565],"iteration":478,"passed_time":4.802502095,"remaining_time":5.223598312},
{"learn":[0.28232707],"iteration":479,"passed_time":4.81240326,"remaining_time":5.213436865},
{"learn":[0.2820751127],"iteration":480,"passed_time":4.821790163,"remaining_time":5.20272161},
{"learn":[0.2818755487],"iteration":481,"passed_time":4.83200798,"remaining_time":5.192904841},
{"learn":[0.2816729584],"iteration":482,"passed_time":4.841829141,"remaining_time":5.182661834},
{"learn":[0.281297418],"iteration":483,"passed_time":4.852564401,"remaining_time":5.173395105},
{"learn":[0.2808618201],"iteration":484,"passed_time":4.864634712,"remaining_time":5.165539952},
{"learn":[0.2803721113],"iteration":485,"passed_time":4.877975111,"remaining_time":5.159010714},
{"learn":[0.2799678238],"iteration":486,"passed_time":4.889870144,"remaining_time":5.150930973},
{"learn":[0.2796828816],"iteration":487,"passed_time":4.901014401,"remaining_time":5.142047896},
{"learn":[0.2792587459],"iteration":488,"passed_time":4.91407984,"remaining_time":5.135163186},
{"learn":[0.2790242227],"iteration":489,"passed_time":4.924722023,"remaining_time":5.125731085},
{"learn":[0.2785803914],"iteration":490,"passed_time":4.936204008,"remaining_time":5.117164644},
{"learn":[0.2784281437],"iteration":491,"passed_time":4.947457016,"remaining_time":5.108349928},
{"learn":[0.2780338511],"iteration":492,"passed_time":4.958555891,"remaining_time":5.099366809},
{"learn":[0.2776942186],"iteration":493,"passed_time":4.968863374,"remaining_time":5.089564508},
{"learn":[0.2775522936],"iteration":494,"passed_time":4.980543019,"remaining_time":5.08116005},
{"learn":[0.2772135023],"iteration":495,"passed_time":4.990535696,"remaining_time":5.071028207},
{"learn":[0.2768744916],"iteration":496,"passed_time":4.998951423,"remaining_time":5.059300937},
{"learn":[0.2765898167],"iteration":497,"passed_time":5.009006644,"remaining_time":5.049239629},
{"learn":[0.2762761673],"iteration":498,"passed_time":5.01825688,"remaining_time":5.038370134},
{"learn":[0.2759339701],"iteration":499,"passed_time":5.028079513,"remaining_time":5.028079513},
{"learn":[0.2753163878],"iteration":500,"passed_time":5.037426905,"remaining_time":5.017317417},
{"learn":[0.2751499283],"iteration":501,"passed_time":5.047848128,"remaining_time":5.00762623},
{"learn":[0.2748950568],"iteration":502,"passed_time":5.058737889,"remaining_time":4.998395091},
{"learn":[0.2747197344],"iteration":503,"passed_time":5.07062016,"remaining_time":4.990134126},
{"learn":[0.2743906848],"iteration":504,"passed_time":5.081650162,"remaining_time":4.981023426},
{"learn":[0.2741518888],"iteration":505,"passed_time":5.090737193,"remaining_time":4.970008248},
{"learn":[0.2739346594],"iteration":506,"passed_time":5.100479285,"remaining_time":4.959637647},
{"learn":[0.2737927713],"iteration":507,"passed_time":5.111834696,"remaining_time":4.950832029},
{"learn":[0.2736029739],"iteration":508,"passed_time":5.120704335,"remaining_time":4.939618524},
{"learn":[0.2733441176],"iteration":509,"passed_time":5.131173608,"remaining_time":4.929951113},
{"learn":[0.2728685411],"iteration":510,"passed_time":5.140574082,"remaining_time":4.919257781},
{"learn":[0.272528923],"iteration":511,"passed_time":5.149869969,"remaining_time":4.908469814},
{"learn":[0.2721139489],"iteration":512,"passed_time":5.159255523,"remaining_time":4.897772787},
{"learn":[0.2716829767],"iteration":513,"passed_time":5.168341134,"remaining_time":4.886797259},
{"learn":[0.2714405151],"iteration":514,"passed_time":5.177514233,"remaining_time":4.875911462},
{"learn":[0.2713152474],"iteration":515,"passed_time":5.186226608,"remaining_time":4.864600152},
{"learn":[0.2708661865],"iteration":516,"passed_time":5.195486142,"remaining_time":4.853810071},
{"learn":[0.2707623538],"iteration":517,"passed_time":5.204576496,"remaining_time":4.842868477},
{"learn":[0.2706788158],"iteration":518,"passed_time":5.213836555,"remaining_time":4.832091297},
{"learn":[0.2703949714],"iteration":519,"passed_time":5.223409027,"remaining_time":4.821608332},
{"learn":[0.2701048516],"iteration":520,"passed_time":5.233176256,"remaining_time":4.81130792},
{"learn":[0.2697161989],"iteration":521,"passed_time":5.245576542,"remaining_time":4.803420665},
{"learn":[0.2696268445],"iteration":522,"passed_time":5.257705799,"remaining_time":4.79526896},
{"learn":[0.2694351522],"iteration":523,"passed_time":5.269439335,"remaining_time":4.786742602},
{"learn":[0.2691807327],"iteration":524,"passed_time":5.279000086,"remaining_time":4.776238173},
{"learn":[0.2689571632],"iteration":525,"passed_time":5.288786556,"remaining_time":4.765940736},
{"learn":[0.2686855448],"iteration":526,"passed_time":5.300790895,"remaining_time":4.757635851},
{"learn":[0.2683235395],"iteration":527,"passed_time":5.313316125,"remaining_time":4.749782596},
{"learn":[0.2680198486],"iteration":528,"passed_time":5.323355242,"remaining_time":4.739698145},
{"learn":[0.267683386],"iteration":529,"passed_time":5.333314481,"remaining_time":4.72954303},
{"learn":[0.2674561187],"iteration":530,"passed_time":5.342879565,"remaining_time":4.71904052},
{"learn":[0.267195065],"iteration":531,"passed_time":5.353326276,"remaining_time":4.7093171},
{"learn":[0.2671080342],"iteration":532,"passed_time":5.36261768,"remaining_time":4.698578718},
{"learn":[0.2667296568],"iteration":533,"passed_time":5.372582345,"remaining_time":4.688433282},
{"learn":[0.2663456762],"iteration":534,"passed_time":5.382534397,"remaining_time":4.67827756},
{"learn":[0.2662532247],"iteration":535,"passed_time":5.392245102,"remaining_time":4.667913671},
{"learn":[0.266052053],"iteration":536,"passed_time":5.401566028,"remaining_time":4.657216147},
{"learn":[0.2658638478],"iteration":537,"passed_time":5.410867273,"remaining_time":4.646506841},
{"learn":[0.2655311925],"iteration":538,"passed_time":5.420701569,"remaining_time":4.63625867},
{"learn":[0.2654183858],"iteration":539,"passed_time":5.430556163,"remaining_time":4.626029324},
{"learn":[0.2649508357],"iteration":540,"passed_time":5.441418894,"remaining_time":4.616656696},
{"learn":[0.2646592601],"iteration":541,"passed_time":5.451645341,"remaining_time":4.606740897},
{"learn":[0.2645061801],"iteration":542,"passed_time":5.464143615,"remaining_time":4.59873597},
{"learn":[0.2641337007],"iteration":543,"passed_time":5.473315727,"remaining_time":4.587926418},
{"learn":[0.2639661231],"iteration":544,"passed_time":5.483614026,"remaining_time":4.578063086},
{"learn":[0.2636820606],"iteration":545,"passed_time":5.496038205,"remaining_time":4.569965834},
{"learn":[0.2634695806],"iteration":546,"passed_time":5.506719244,"remaining_time":4.560409173},
{"learn":[0.2631843593],"iteration":547,"passed_time":5.516968484,"remaining_time":4.550492253},
{"learn":[0.2630127595],"iteration":548,"passed_time":5.527573914,"remaining_time":4.540866731},
{"learn":[0.2627327501],"iteration":549,"passed_time":5.5378103,"remaining_time":4.5309357},
{"learn":[0.2624619286],"iteration":550,"passed_time":5.547725261,"remaining_time":4.520741637},
{"learn":[0.2622585433],"iteration":551,"passed_time":5.55767939,"remaining_time":4.510580375},
{"learn":[0.2618836451],"iteration":552,"passed_time":5.568493998,"remaining_time":4.501115402},
{"learn":[0.2615329374],"iteration":553,"passed_time":5.579454053,"remaining_time":4.491762649},
{"learn":[0.2612379243],"iteration":554,"passed_time":5.589525583,"remaining_time":4.481691684},
{"learn":[0.2610152566],"iteration":555,"passed_time":5.599282274,"remaining_time":4.471369298},
{"learn":[0.2608256771],"iteration":556,"passed_time":5.608867655,"remaining_time":4.460912695},
{"learn":[0.2607573156],"iteration":557,"passed_time":5.617697214,"remaining_time":4.449860517},
{"learn":[0.2606400322],"iteration":558,"passed_time":5.626510604,"remaining_time":4.438803535},
{"learn":[0.2605260367],"iteration":559,"passed_time":5.636380336,"remaining_time":4.428584549},
{"learn":[0.2601553136],"iteration":560,"passed_time":5.64661828,"remaining_time":4.418654946},
{"learn":[0.2600736435],"iteration":561,"passed_time":5.658585351,"remaining_time":4.410071857},
{"learn":[0.2597194035],"iteration":562,"passed_time":5.67046925,"remaining_time":4.401412189},
{"learn":[0.2596053539],"iteration":563,"passed_time":5.680122248,"remaining_time":4.39101649},
{"learn":[0.259432182],"iteration":564,"passed_time":5.689140538,"remaining_time":4.38013475},
{"learn":[0.2588151157],"iteration":565,"passed_time":5.700863672,"remaining_time":4.371333628},
{"learn":[0.2585294982],"iteration":566,"passed_time":5.711619787,"remaining_time":4.361783718},
{"learn":[0.2582320757],"iteration":567,"passed_time":5.720693507,"remaining_time":4.350949991},
{"learn":[0.2578840697],"iteration":568,"passed_time":5.730621088,"remaining_time":4.340769225},
{"learn":[0.257790498],"iteration":569,"passed_time":5.740339023,"remaining_time":4.330431193},
{"learn":[0.2573427832],"iteration":570,"passed_time":5.749984141,"remaining_time":4.320040624},
{"learn":[0.2571166951],"iteration":571,"passed_time":5.761107828,"remaining_time":4.310759004},
{"learn":[0.2568438578],"iteration":572,"passed_time":5.771035313,"remaining_time":4.300579544},
{"learn":[0.2566298983],"iteration":573,"passed_time":5.781507103,"remaining_time":4.290804923},
{"learn":[0.2562740807],"iteration":574,"passed_time":5.791938676,"remaining_time":4.280998152},
{"learn":[0.2559599542],"iteration":575,"passed_time":5.802772068,"remaining_time":4.271484994},
{"learn":[0.2556409019],"iteration":576,"passed_time":5.81424494,"remaining_time":4.262436065},
{"learn":[0.2553325865],"iteration":577,"passed_time":5.824477792,"remaining_time":4.252473405},
{"learn":[0.2551122779],"iteration":578,"passed_time":5.836882219,"remaining_time":4.244088798},
{"learn":[0.2549105411],"iteration":579,"passed_time":5.84875205,"remaining_time":4.235303209},
{"learn":[0.2547122974],"iteration":580,"passed_time":5.860637875,"remaining_time":4.226518536},
{"learn":[0.2544439435],"iteration":581,"passed_time":5.87017256,"remaining_time":4.216034587},
{"learn":[0.2542242817],"iteration":582,"passed_time":5.880054831,"remaining_time":4.205802512},
{"learn":[0.2540023401],"iteration":583,"passed_time":5.892068258,"remaining_time":4.197089718},
{"learn":[0.2539163412],"iteration":584,"passed_time":5.901395839,"remaining_time":4.186460296},
{"learn":[0.2537943278],"iteration":585,"passed_time":5.911364416,"remaining_time":4.176288171},
{"learn":[0.2536028158],"iteration":586,"passed_time":5.920237476,"remaining_time":4.165345958},
{"learn":[0.2534159822],"iteration":587,"passed_time":5.929444636,"remaining_time":4.154644881},
{"learn":[0.2530930528],"iteration":588,"passed_time":5.939292949,"remaining_time":4.144396268},
{"learn":[0.252894965],"iteration":589,"passed_time":5.949827668,"remaining_time":4.134626006},
{"learn":[0.2527084741],"iteration":590,"passed_time":5.95985509,"remaining_time":4.124502084},
{"learn":[0.2525253317],"iteration":591,"passed_time":5.969437375,"remaining_time":4.114071705},
{"learn":[0.2523001845],"iteration":592,"passed_time":5.979574218,"remaining_time":4.1040248},
{"learn":[0.2521234639],"iteration":593,"passed_time":5.989933572,"remaining_time":4.09412968},
{"learn":[0.2520112968],"iteration":594,"passed_time":5.998890809,"remaining_time":4.083278618},
{"learn":[0.2518899],"iteration":595,"passed_time":6.009630912,"remaining_time":4.07364243},
{"learn":[0.251717383],"iteration":596,"passed_time":6.020871276,"remaining_time":4.064340242},
{"learn":[0.2516282585],"iteration":597,"passed_time":6.034140121,"remaining_time":4.056395198},
{"learn":[0.251210275],"iteration":598,"passed_time":6.046085443,"remaining_time":4.047546348},
{"learn":[0.2509188497],"iteration":599,"passed_time":6.057172927,"remaining_time":4.038115285},
{"learn":[0.2506033436],"iteration":600,"passed_time":6.0715082,"remaining_time":4.030834895},
{"learn":[0.2503541112],"iteration":601,"passed_time":6.080981025,"remaining_time":4.020316359},
{"learn":[0.2500198803],"iteration":602,"passed_time":6.091714932,"remaining_time":4.010631555},
{"learn":[0.2497954706],"iteration":603,"passed_time":6.101633611,"remaining_time":4.000408792},
{"learn":[0.249727383],"iteration":604,"passed_time":6.111049969,"remaining_time":3.989859071},
{"learn":[0.2494675898],"iteration":605,"passed_time":6.12043253,"remaining_time":3.979291117},
{"learn":[0.2492815651],"iteration":606,"passed_time":6.129860656,"remaining_time":3.96875657},
{"learn":[0.2490973852],"iteration":607,"passed_time":6.138541282,"remaining_time":3.957743722},
{"learn":[0.2489863512],"iteration":608,"passed_time":6.14923056,"remaining_time":3.948028159},
{"learn":[0.2486374141],"iteration":609,"passed_time":6.158824801,"remaining_time":3.937609299},
{"learn":[0.2485668497],"iteration":610,"passed_time":6.168451447,"remaining_time":3.927213769},
{"learn":[0.2481498064],"iteration":611,"passed_time":6.177945302,"remaining_time":3.916736564},
{"learn":[0.2479389266],"iteration":612,"passed_time":6.188082938,"remaining_time":3.906669},
{"learn":[0.2477762848],"iteration":613,"passed_time":6.198154025,"remaining_time":3.896559371},
{"learn":[0.2473532288],"iteration":614,"passed_time":6.208008355,"remaining_time":3.886314174},
{"learn":[0.2471896602],"iteration":615,"passed_time":6.217252215,"remaining_time":3.875689693},
{"learn":[0.2469296224],"iteration":616,"passed_time":6.226972978,"remaining_time":3.865365722},
{"learn":[0.2468018894],"iteration":617,"passed_time":6.236593061,"remaining_time":3.854981472},
{"learn":[0.2466457783],"iteration":618,"passed_time":6.247826177,"remaining_time":3.845592526},
{"learn":[0.2464562528],"iteration":619,"passed_time":6.25817482,"remaining_time":3.835655535},
{"learn":[0.2458250613],"iteration":620,"passed_time":6.2687429,"remaining_time":3.825851142},
{"learn":[0.2456441667],"iteration":621,"passed_time":6.281948442,"remaining_time":3.817647124},
{"learn":[0.2453582881],"iteration":622,"passed_time":6.294000528,"remaining_time":3.808729052},
{"learn":[0.245154422],"iteration":623,"passed_time":6.303669011,"remaining_time":3.798364661},
{"learn":[0.2449768184],"iteration":624,"passed_time":6.312895324,"remaining_time":3.787737195},
{"learn":[0.2447944125],"iteration":625,"passed_time":6.32209559,"remaining_time":3.777098643},
{"learn":[0.2445791211],"iteration":626,"passed_time":6.331952426,"remaining_time":3.766855271},
{"learn":[0.2444602528],"iteration":627,"passed_time":6.340822844,"remaining_time":3.756028819},
{"learn":[0.2443107961],"iteration":628,"passed_time":6.350106178,"remaining_time":3.745452133},
{"learn":[0.244113394],"iteration":629,"passed_time":6.361122784,"remaining_time":3.735897508},
{"learn":[0.2439251126],"iteration":630,"passed_time":6.371610954,"remaining_time":3.726029227},
{"learn":[0.2436418899],"iteration":631,"passed_time":6.381539215,"remaining_time":3.715832961},
{"learn":[0.2435273061],"iteration":632,"passed_time":6.390246843,"remaining_time":3.704929844},
{"learn":[0.2433025269],"iteration":633,"passed_time":6.398848498,"remaining_time":3.693972477},
{"learn":[0.2431188832],"iteration":634,"passed_time":6.409154151,"remaining_time":3.684001992},
{"learn":[0.2428925083],"iteration":635,"passed_time":6.419996719,"remaining_time":3.674337745},
{"learn":[0.2426038509],"iteration":636,"passed_time":6.429546172,"remaining_time":3.663932905},
{"learn":[0.2423829448],"iteration":637,"passed_time":6.439925759,"remaining_time":3.654001763},
{"learn":[0.2422060218],"iteration":638,"passed_time":6.450729496,"remaining_time":3.644308839},
{"learn":[0.2419760231],"iteration":639,"passed_time":6.461155954,"remaining_time":3.634400224},
{"learn":[0.2417634383],"iteration":640,"passed_time":6.474011692,"remaining_time":3.625850542},
{"learn":[0.2415613776],"iteration":641,"passed_time":6.483733093,"remaining_time":3.615539637},
{"learn":[0.2414208468],"iteration":642,"passed_time":6.492835499,"remaining_time":3.604886894},
{"learn":[0.2411103009],"iteration":643,"passed_time":6.503858945,"remaining_time":3.595300907},
{"learn":[0.2408083493],"iteration":644,"passed_time":6.513878907,"remaining_time":3.585158158},
{"learn":[0.2407294682],"iteration":645,"passed_time":6.523319248,"remaining_time":3.574698164},
{"learn":[0.2404859102],"iteration":646,"passed_time":6.531911111,"remaining_time":3.563778396},
{"learn":[0.2404078066],"iteration":647,"passed_time":6.541094337,"remaining_time":3.553187047},
{"learn":[0.2401706092],"iteration":648,"passed_time":6.550244759,"remaining_time":3.542582296},
{"learn":[0.2399944301],"iteration":649,"passed_time":6.559936776,"remaining_time":3.532273649},
{"learn":[0.2398470832],"iteration":650,"passed_time":6.569295152,"remaining_time":3.521788031},
{"learn":[0.2397052186],"iteration":651,"passed_time":6.578348963,"remaining_time":3.511143312},
{"learn":[0.2394577912],"iteration":652,"passed_time":6.587808786,"remaining_time":3.500719217},
{"learn":[0.2392227682],"iteration":653,"passed_time":6.596549635,"remaining_time":3.489917697},
{"learn":[0.2389112715],"iteration":654,"passed_time":6.606199889,"remaining_time":3.479601468},
{"learn":[0.2385747621],"iteration":655,"passed_time":6.615805085,"remaining_time":3.469263642},
{"learn":[0.2383302577],"iteration":656,"passed_time":6.625854164,"remaining_time":3.459159784},
{"learn":[0.2381113965],"iteration":657,"passed_time":6.636537375,"remaining_time":3.449385687},
{"learn":[0.2378152124],"iteration":658,"passed_time":6.648025698,"remaining_time":3.440025437},
{"learn":[0.2376933984],"iteration":659,"passed_time":6.658816996,"remaining_time":3.430299664},
{"learn":[0.2375253275],"iteration":660,"passed_time":6.670816279,"remaining_time":3.421190195},
{"learn":[0.2373221665],"iteration":661,"passed_time":6.680741281,"remaining_time":3.41101292},
{"learn":[0.2370754806],"iteration":662,"passed_time":6.691598216,"remaining_time":3.401310104},
{"learn":[0.236849599],"iteration":663,"passed_time":6.703722336,"remaining_time":3.392245038},
{"learn":[0.2365919962],"iteration":664,"passed_time":6.713876851,"remaining_time":3.382178564},
{"learn":[0.2363830814],"iteration":665,"passed_time":6.72423442,"remaining_time":3.372213658},
{"learn":[0.2363052536],"iteration":666,"passed_time":6.733007076,"remaining_time":3.361456306},
{"learn":[0.235919802],"iteration":667,"passed_time":6.742031866,"remaining_time":3.350830209},
{"learn":[0.2358507874],"iteration":668,"passed_time":6.751083216,"remaining_time":3.34022204},
{"learn":[0.2356468949],"iteration":669,"passed_time":6.760487652,"remaining_time":3.329792426},
{"learn":[0.2354492137],"iteration":670,"passed_time":6.770123194,"remaining_time":3.319479181},
{"learn":[0.2352598884],"iteration":671,"passed_time":6.779240265,"remaining_time":3.308914891},
{"learn":[0.2351818974],"iteration":672,"passed_time":6.788559294,"remaining_time":3.29845303},
{"learn":[0.2349744215],"iteration":673,"passed_time":6.799030888,"remaining_time":3.288552032},
{"learn":[0.2348494677],"iteration":674,"passed_time":6.808386612,"remaining_time":3.278112073},
{"learn":[0.2346699472],"iteration":675,"passed_time":6.817695805,"remaining_time":3.267653019},
{"learn":[0.2345850123],"iteration":676,"passed_time":6.826645733,"remaining_time":3.257025955},
{"learn":[0.2344314233],"iteration":677,"passed_time":6.836620698,"remaining_time":3.246890656},
{"learn":[0.2342136022],"iteration":678,"passed_time":6.847403679,"remaining_time":3.237137822},
{"learn":[0.2340958816],"iteration":679,"passed_time":6.859518303,"remaining_time":3.228008613},
{"learn":[0.2340431315],"iteration":680,"passed_time":6.868708013,"remaining_time":3.217500523},
{"learn":[0.2338724129],"iteration":681,"passed_time":6.879818824,"remaining_time":3.207892062},
{"learn":[0.2337297379],"iteration":682,"passed_time":6.88996998,"remaining_time":3.197833798},
{"learn":[0.2335489854],"iteration":683,"passed_time":6.899337811,"remaining_time":3.187413375},
{"learn":[0.2333520632],"iteration":684,"passed_time":6.911342527,"remaining_time":3.178208607},
{"learn":[0.2330161884],"iteration":685,"passed_time":6.921989428,"remaining_time":3.16837417},
{"learn":[0.2328633267],"iteration":686,"passed_time":6.931210064,"remaining_time":3.157887555},
{"learn":[0.2326156292],"iteration":687,"passed_time":6.939765526,"remaining_time":3.147102971},
{"learn":[0.232330776],"iteration":688,"passed_time":6.949497991,"remaining_time":3.136856133},
{"learn":[0.2321252689],"iteration":689,"passed_time":6.959214088,"remaining_time":3.126603431},
{"learn":[0.2320256034],"iteration":690,"passed_time":6.968504292,"remaining_time":3.116161832},
{"learn":[0.2319142785],"iteration":691,"passed_time":6.977513261,"remaining_time":3.105598388},
{"learn":[0.2316607251],"iteration":692,"passed_time":6.98715167,"remaining_time":3.095318272},
{"learn":[0.2313972749],"iteration":693,"passed_time":6.996545755,"remaining_time":3.084932278},
{"learn":[0.2312919671],"iteration":694,"passed_time":7.006247357,"remaining_time":3.074684092},
{"learn":[0.2309520029],"iteration":695,"passed_time":7.015723285,"remaining_time":3.064338906},
{"learn":[0.2306169025],"iteration":696,"passed_time":7.027043329,"remaining_time":3.054797889},
{"learn":[0.2305059561],"iteration":697,"passed_time":7.035775037,"remaining_time":3.044131893},
{"learn":[0.2304051091],"iteration":698,"passed_time":7.046272115,"remaining_time":3.034231626},
{"learn":[0.2302345887],"iteration":699,"passed_time":7.057000062,"remaining_time":3.024428598},
{"learn":[0.2299388433],"iteration":700,"passed_time":7.06872822,"remaining_time":3.015049555},
{"learn":[0.2296733547],"iteration":701,"passed_time":7.08087352,"remaining_time":3.005840896},
{"learn":[0.2293004283],"iteration":702,"passed_time":7.090904865,"remaining_time":2.995730789},
{"learn":[0.2291724038],"iteration":703,"passed_time":7.103842473,"remaining_time":2.986842858},
{"learn":[0.2290300065],"iteration":704,"passed_time":7.114570781,"remaining_time":2.977018979},
{"learn":[0.228897998],"iteration":705,"passed_time":7.125029315,"remaining_time":2.967080196},
{"learn":[0.2285592833],"iteration":706,"passed_time":7.134855562,"remaining_time":2.956877906},
{"learn":[0.228385841],"iteration":707,"passed_time":7.144819069,"remaining_time":2.946733288},
{"learn":[0.2281428747],"iteration":708,"passed_time":7.15443753,"remaining_time":2.936447562},
{"learn":[0.2278742471],"iteration":709,"passed_time":7.165239193,"remaining_time":2.926646994},
{"learn":[0.2277117984],"iteration":710,"passed_time":7.175361884,"remaining_time":2.91656763},
{"learn":[0.2275972518],"iteration":711,"passed_time":7.184864465,"remaining_time":2.906237312},
{"learn":[0.227487088],"iteration":712,"passed_time":7.194079538,"remaining_time":2.895793587},
{"learn":[0.2273670115],"iteration":713,"passed_time":7.204557534,"remaining_time":2.88585918},
{"learn":[0.2271923614],"iteration":714,"passed_time":7.213450609,"remaining_time":2.875291502},
{"learn":[0.2270695736],"iteration":715,"passed_time":7.22300617,"remaining_time":2.864991274},
{"learn":[0.2269033267],"iteration":716,"passed_time":7.232716668,"remaining_time":2.854754277},
{"learn":[0.2267248644],"iteration":717,"passed_time":7.243837487,"remaining_time":2.845072662},
{"learn":[0.2266466506],"iteration":718,"passed_time":7.25376692,"remaining_time":2.834921425},
{"learn":[0.2264530188],"iteration":719,"passed_time":7.264496782,"remaining_time":2.825082082},
{"learn":[0.2262053399],"iteration":720,"passed_time":7.276488394,"remaining_time":2.815728519},
{"learn":[0.2260794967],"iteration":721,"passed_time":7.285280316,"remaining_time":2.805135634},
{"learn":[0.2258696707],"iteration":722,"passed_time":7.296000774,"remaining_time":2.795286604},
{"learn":[0.2258025301],"iteration":723,"passed_time":7.305844105,"remaining_time":2.785100791},
{"learn":[0.2254226908],"iteration":724,"passed_time":7.3158272,"remaining_time":2.774968938},
{"learn":[0.2252096122],"iteration":725,"passed_time":7.325775831,"remaining_time":2.764824487},
{"learn":[0.225178508],"iteration":726,"passed_time":7.335182111,"remaining_time":2.754476914},
{"learn":[0.2248715764],"iteration":727,"passed_time":7.345437704,"remaining_time":2.744449252},
{"learn":[0.2247312367],"iteration":728,"passed_time":7.354331884,"remaining_time":2.733914871},
{"learn":[0.2245591161],"iteration":729,"passed_time":7.363517905,"remaining_time":2.723492924},
{"learn":[0.2243802937],"iteration":730,"passed_time":7.373360073,"remaining_time":2.713315814},
{"learn":[0.2242536161],"iteration":731,"passed_time":7.382421771,"remaining_time":2.702853872},
{"learn":[0.2241179141],"iteration":732,"passed_time":7.392050356,"remaining_time":2.692602244},
{"learn":[0.2239446268],"iteration":733,"passed_time":7.401227972,"remaining_time":2.682188884},
{"learn":[0.2236920324],"iteration":734,"passed_time":7.410829891,"remaining_time":2.671931865},
{"learn":[0.2234980359],"iteration":735,"passed_time":7.420705338,"remaining_time":2.661774741},
{"learn":[0.2234368609],"iteration":736,"passed_time":7.430015142,"remaining_time":2.65141653},
{"learn":[0.2232926176],"iteration":737,"passed_time":7.441161471,"remaining_time":2.641713151},
{"learn":[0.2231786131],"iteration":738,"passed_time":7.453245897,"remaining_time":2.632337184},
{"learn":[0.2229819954],"iteration":739,"passed_time":7.466711419,"remaining_time":2.623439147},
{"learn":[0.2227341521],"iteration":740,"passed_time":7.476176719,"remaining_time":2.613130594},
{"learn":[0.2225231774],"iteration":741,"passed_time":7.487416671,"remaining_time":2.603441376},
{"learn":[0.2223559075],"iteration":742,"passed_time":7.500591859,"remaining_time":2.594417373},
{"learn":[0.2221983396],"iteration":743,"passed_time":7.510026839,"remaining_time":2.584095257},
{"learn":[0.2221136115],"iteration":744,"passed_time":7.520418455,"remaining_time":2.574102961},
{"learn":[0.2219954251],"iteration":745,"passed_time":7.531074706,"remaining_time":2.564199699},
{"learn":[0.2218772491],"iteration":746,"passed_time":7.541024485,"remaining_time":2.554055147},
{"learn":[0.2218299305],"iteration":747,"passed_time":7.550992201,"remaining_time":2.543917159},
{"learn":[0.2216867068],"iteration":748,"passed_time":7.560806869,"remaining_time":2.533728337},
{"learn":[0.2213911305],"iteration":749,"passed_time":7.570262902,"remaining_time":2.523420967},
{"learn":[0.2212947658],"iteration":750,"passed_time":7.579195388,"remaining_time":2.512942279},
{"learn":[0.2211074873],"iteration":751,"passed_time":7.590036303,"remaining_time":2.503097079},
{"learn":[0.2209160778],"iteration":752,"passed_time":7.602329051,"remaining_time":2.493725466},
{"learn":[0.2204631709],"iteration":753,"passed_time":7.612068567,"remaining_time":2.483513087},
{"learn":[0.2203462784],"iteration":754,"passed_time":7.621315104,"remaining_time":2.473141987},
{"learn":[0.2201300249],"iteration":755,"passed_time":7.632086544,"remaining_time":2.463266027},
{"learn":[0.2199432998],"iteration":756,"passed_time":7.643211856,"remaining_time":2.453501296},
{"learn":[0.2196510177],"iteration":757,"passed_time":7.655868916,"remaining_time":2.444222002},
{"learn":[0.2195031249],"iteration":758,"passed_time":7.666216712,"remaining_time":2.434200563},
{"learn":[0.2192864617],"iteration":759,"passed_time":7.675909027,"remaining_time":2.423971272},
{"learn":[0.2190934997],"iteration":760,"passed_time":7.685176318,"remaining_time":2.413609908},
{"learn":[0.2190379131],"iteration":761,"passed_time":7.694045417,"remaining_time":2.403127046},
{"learn":[0.2189636854],"iteration":762,"passed_time":7.704116213,"remaining_time":2.393021681},
{"learn":[0.2187811238],"iteration":763,"passed_time":7.714836308,"remaining_time":2.383116975},
{"learn":[0.2186906557],"iteration":764,"passed_time":7.723603928,"remaining_time":2.372610357},
{"learn":[0.2185101965],"iteration":765,"passed_time":7.732791819,"remaining_time":2.362236665},
{"learn":[0.2184258785],"iteration":766,"passed_time":7.74225905,"remaining_time":2.351950924},
{"learn":[0.218248833],"iteration":767,"passed_time":7.751461652,"remaining_time":2.341587374},
{"learn":[0.2180520214],"iteration":768,"passed_time":7.761515222,"remaining_time":2.331482466},
{"learn":[0.2179591107],"iteration":769,"passed_time":7.771495334,"remaining_time":2.321355749},
{"learn":[0.2178297804],"iteration":770,"passed_time":7.780902616,"remaining_time":2.311059272},
{"learn":[0.217714941],"iteration":771,"passed_time":7.790020859,"remaining_time":2.300679736},
{"learn":[0.2174862765],"iteration":772,"passed_time":7.798777142,"remaining_time":2.290197169},
{"learn":[0.2171830785],"iteration":773,"passed_time":7.808007848,"remaining_time":2.279857589},
{"learn":[0.2170843352],"iteration":774,"passed_time":7.817552587,"remaining_time":2.269612041},
{"learn":[0.2168637817],"iteration":775,"passed_time":7.827222228,"remaining_time":2.259404354},
{"learn":[0.216690558],"iteration":776,"passed_time":7.83736628,"remaining_time":2.249334209},
{"learn":[0.2166306581],"iteration":777,"passed_time":7.847531833,"remaining_time":2.239270009},
{"learn":[0.2164445603],"iteration":778,"passed_time":7.857653314,"remaining_time":2.229193045},
{"learn":[0.2162895751],"iteration":779,"passed_time":7.869276257,"remaining_time":2.219539457},
{"learn":[0.2161147306],"iteration":780,"passed_time":7.878928683,"remaining_time":2.209328274},
{"learn":[0.2158557771],"iteration":781,"passed_time":7.888377413,"remaining_time":2.199061734},
{"learn":[0.2157775056],"iteration":782,"passed_time":7.899146267,"remaining_time":2.189163142},
{"learn":[0.2156257482],"iteration":783,"passed_time":7.908932589,"remaining_time":2.178991632},
{"learn":[0.2154502195],"iteration":784,"passed_time":7.917855607,"remaining_time":2.168584657},
{"learn":[0.2153659937],"iteration":785,"passed_time":7.927348224,"remaining_time":2.158336539},
{"learn":[0.2152071446],"iteration":786,"passed_time":7.937093636,"remaining_time":2.14815876},
{"learn":[0.2150020817],"iteration":787,"passed_time":7.94738459,"remaining_time":2.138128849},
{"learn":[0.2148199847],"iteration":788,"passed_time":7.957288288,"remaining_time":2.127994713},
{"learn":[0.2145392098],"iteration":789,"passed_time":7.967112282,"remaining_time":2.117839974},
{"learn":[0.2144220024],"iteration":790,"passed_time":7.975736499,"remaining_time":2.107369062},
{"learn":[0.2142933829],"iteration":791,"passed_time":7.984958056,"remaining_time":2.097059691},
{"learn":[0.2141613613],"iteration":792,"passed_time":7.993688433,"remaining_time":2.086624849},
{"learn":[0.2138063298],"iteration":793,"passed_time":8.003562716,"remaining_time":2.076491083},
{"learn":[0.2136444072],"iteration":794,"passed_time":8.013064876,"remaining_time":2.066262012},
{"learn":[0.2134442295],"iteration":795,"passed_time":8.023101108,"remaining_time":2.056171641},
{"learn":[0.2133397657],"iteration":796,"passed_time":8.032439645,"remaining_time":2.045903699},
{"learn":[0.2131694759],"iteration":797,"passed_time":8.043051505,"remaining_time":2.035960406},
{"learn":[0.2129610707],"iteration":798,"passed_time":8.054271648,"remaining_time":2.026168462},
{"learn":[0.2128753876],"iteration":799,"passed_time":8.067143228,"remaining_time":2.016785807},
{"learn":[0.2126370867],"iteration":800,"passed_time":8.077231607,"remaining_time":2.006702984},
{"learn":[0.2124696157],"iteration":801,"passed_time":8.087149017,"remaining_time":1.996577937},
{"learn":[0.2123369115],"iteration":802,"passed_time":8.09889447,"remaining_time":1.986901881},
{"learn":[0.2121954133],"iteration":803,"passed_time":8.108743066,"remaining_time":1.97675826},
{"learn":[0.2120650089],"iteration":804,"passed_time":8.118532775,"remaining_time":1.966601107},
{"learn":[0.2118423716],"iteration":805,"passed_time":8.12856969,"remaining_time":1.956504367},
{"learn":[0.2117037625],"iteration":806,"passed_time":8.138058374,"remaining_time":1.946276662},
{"learn":[0.2116536668],"iteration":807,"passed_time":8.148147429,"remaining_time":1.936193448},
{"learn":[0.211533867],"iteration":808,"passed_time":8.156904396,"remaining_time":1.925795723},
{"learn":[0.2113420295],"iteration":809,"passed_time":8.165937695,"remaining_time":1.915466867},
{"learn":[0.211214098],"iteration":810,"passed_time":8.17653375,"remaining_time":1.905505399},
{"learn":[0.2111368854],"iteration":811,"passed_time":8.18560811,"remaining_time":1.895190055},
{"learn":[0.2109747431],"iteration":812,"passed_time":8.195153217,"remaining_time":1.884986041},
{"learn":[0.2108761413],"iteration":813,"passed_time":8.204898381,"remaining_time":1.87482936},
{"learn":[0.2107191337],"iteration":814,"passed_time":8.2140341,"remaining_time":1.864535348},
{"learn":[0.2105614846],"iteration":815,"passed_time":8.223909806,"remaining_time":1.854411035},
{"learn":[0.2103430247],"iteration":816,"passed_time":8.234111715,"remaining_time":1.844360396},
{"learn":[0.2101443649],"iteration":817,"passed_time":8.245375047,"remaining_time":1.834545548},
{"learn":[0.2099492005],"iteration":818,"passed_time":8.258276344,"remaining_time":1.825089155},
{"learn":[0.2098038762],"iteration":819,"passed_time":8.267899549,"remaining_time":1.814904779},
{"learn":[0.2096950096],"iteration":820,"passed_time":8.277502351,"remaining_time":1.804717321},
{"learn":[0.2094691144],"iteration":821,"passed_time":8.286735392,"remaining_time":1.794451216},
{"learn":[0.2092363577],"iteration":822,"passed_time":8.29695258,"remaining_time":1.784399279},
{"learn":[0.209132096],"iteration":823,"passed_time":8.30930059,"remaining_time":1.774802068},
{"learn":[0.208897829],"iteration":824,"passed_time":8.320948447,"remaining_time":1.765049671},
{"learn":[0.2088174857],"iteration":825,"passed_time":8.332204997,"remaining_time":1.755210254},
{"learn":[0.208718953],"iteration":826,"passed_time":8.342672326,"remaining_time":1.745202312},
{"learn":[0.2084741545],"iteration":827,"passed_time":8.35269253,"remaining_time":1.735100381},
{"learn":[0.2083975513],"iteration":828,"passed_time":8.36379429,"remaining_time":1.725221741},
{"learn":[0.2082902707],"iteration":829,"passed_time":8.3741566,"remaining_time":1.715188701},
{"learn":[0.2081882697],"iteration":830,"passed_time":8.384195947,"remaining_time":1.705089188},
{"learn":[0.2081259454],"iteration":831,"passed_time":8.393848537,"remaining_time":1.694911724},
{"learn":[0.2079300619],"iteration":832,"passed_time":8.404248126,"remaining_time":1.684885278},
{"learn":[0.2077030642],"iteration":833,"passed_time":8.413254066,"remaining_time":1.674580546},
{"learn":[0.2075756933],"iteration":834,"passed_time":8.422748206,"remaining_time":1.664375394},
{"learn":[0.2071408935],"iteration":835,"passed_time":8.432767977,"remaining_time":1.654275058},
{"learn":[0.2069786568],"iteration":836,"passed_time":8.44336936,"remaining_time":1.644288179},
{"learn":[0.2066612547],"iteration":837,"passed_time":8.454040002,"remaining_time":1.634313222},
{"learn":[0.2065901355],"iteration":838,"passed_time":8.464212984,"remaining_time":1.624241109},
{"learn":[0.2062776602],"iteration":839,"passed_time":8.476277127,"remaining_time":1.614528977},
{"learn":[0.2060272633],"iteration":840,"passed_time":8.485870761,"remaining_time":1.604344175},
{"learn":[0.2059321843],"iteration":841,"passed_time":8.496987839,"remaining_time":1.594446649},
{"learn":[0.2057667013],"iteration":842,"passed_time":8.5071889,"remaining_time":1.584375632},
{"learn":[0.2057323906],"iteration":843,"passed_time":8.515081767,"remaining_time":1.573877673},
{"learn":[0.2055251153],"iteration":844,"passed_time":8.52429043,"remaining_time":1.563627239},
{"learn":[0.2053554888],"iteration":845,"passed_time":8.534251739,"remaining_time":1.553516274},
{"learn":[0.2052492948],"iteration":846,"passed_time":8.544200743,"remaining_time":1.54340344},
{"learn":[0.2051040358],"iteration":847,"passed_time":8.554661352,"remaining_time":1.533382695},
{"learn":[0.2049924166],"iteration":848,"passed_time":8.564886189,"remaining_time":1.523318981},
{"learn":[0.2048473977],"iteration":849,"passed_time":8.575041723,"remaining_time":1.513242657},
{"learn":[0.2047128013],"iteration":850,"passed_time":8.58525762,"remaining_time":1.503176716},
{"learn":[0.2044960672],"iteration":851,"passed_time":8.594602709,"remaining_time":1.492959156},
{"learn":[0.204306524],"iteration":852,"passed_time":8.605679833,"remaining_time":1.483042128},
{"learn":[0.2042296123],"iteration":853,"passed_time":8.616393908,"remaining_time":1.473060317},
{"learn":[0.2041441933],"iteration":854,"passed_time":8.626510559,"remaining_time":1.462975475},
{"learn":[0.2040393792],"iteration":855,"passed_time":8.636866194,"remaining_time":1.452930762},
{"learn":[0.2038658042],"iteration":856,"passed_time":8.647781912,"remaining_time":1.442978779},
{"learn":[0.2036966771],"iteration":857,"passed_time":8.660283367,"remaining_time":1.433286991},
{"learn":[0.2035489669],"iteration":858,"passed_time":8.672741333,"remaining_time":1.423581523},
{"learn":[0.2034247673],"iteration":859,"passed_time":8.682302356,"remaining_time":1.413398058},
{"learn":[0.2032396554],"iteration":860,"passed_time":8.693981053,"remaining_time":1.403557917},
{"learn":[0.2030338657],"iteration":861,"passed_time":8.704710363,"remaining_time":1.39356152},
{"learn":[0.202744945],"iteration":862,"passed_time":8.715186828,"remaining_time":1.383523286},
{"learn":[0.2026083851],"iteration":863,"passed_time":8.724519851,"remaining_time":1.373304051},
{"learn":[0.2023872525],"iteration":864,"passed_time":8.734177931,"remaining_time":1.363137596},
{"learn":[0.2022488237],"iteration":865,"passed_time":8.744481649,"remaining_time":1.353072218},
{"learn":[0.2021432511],"iteration":866,"passed_time":8.754715104,"remaining_time":1.342995512},
{"learn":[0.2020462792],"iteration":867,"passed_time":8.76440258,"remaining_time":1.332835415},
{"learn":[0.2019464899],"iteration":868,"passed_time":8.774410074,"remaining_time":1.322724649},
{"learn":[0.2018060317],"iteration":869,"passed_time":8.783943238,"remaining_time":1.312543242},
{"learn":[0.2016756414],"iteration":870,"passed_time":8.793120265,"remaining_time":1.302310579},
{"learn":[0.2015335417],"iteration":871,"passed_time":8.802539999,"remaining_time":1.292115963},
{"learn":[0.2013971804],"iteration":872,"passed_time":8.812166457,"remaining_time":1.281953196},
{"learn":[0.2013167164],"iteration":873,"passed_time":8.821630624,"remaining_time":1.271768259},
{"learn":[0.2011707102],"iteration":874,"passed_time":8.830966544,"remaining_time":1.261566649},
{"learn":[0.2009671713],"iteration":875,"passed_time":8.840981695,"remaining_time":1.251463162},
{"learn":[0.2007834979],"iteration":876,"passed_time":8.852035713,"remaining_time":1.241505579},
{"learn":[0.2006211991],"iteration":877,"passed_time":8.863421945,"remaining_time":1.23159166},
{"learn":[0.2004433147],"iteration":878,"passed_time":8.872333749,"remaining_time":1.22133377},
{"learn":[0.2003673142],"iteration":879,"passed_time":8.883499752,"remaining_time":1.21138633},
{"learn":[0.2002414598],"iteration":880,"passed_time":8.893910829,"remaining_time":1.201334153},
{"learn":[0.2001250322],"iteration":881,"passed_time":8.904418903,"remaining_time":1.191294139},
{"learn":[0.2000173316],"iteration":882,"passed_time":8.916415566,"remaining_time":1.181450307},
{"learn":[0.1998432329],"iteration":883,"passed_time":8.926336224,"remaining_time":1.171329188},
{"learn":[0.1996922822],"iteration":884,"passed_time":8.935854838,"remaining_time":1.161156278},
{"learn":[0.1995040607],"iteration":885,"passed_time":8.945795554,"remaining_time":1.151039157},
{"learn":[0.1993476544],"iteration":886,"passed_time":8.955279774,"remaining_time":1.140864278},
{"learn":[0.1992109364],"iteration":887,"passed_time":8.966416678,"remaining_time":1.130899401},
{"learn":[0.1989422964],"iteration":888,"passed_time":8.976352257,"remaining_time":1.12078189},
{"learn":[0.1986612933],"iteration":889,"passed_time":8.986673321,"remaining_time":1.110712433},
{"learn":[0.1984785955],"iteration":890,"passed_time":8.996960272,"remaining_time":1.100638237},
{"learn":[0.1983476992],"iteration":891,"passed_time":9.007580136,"remaining_time":1.090603873},
{"learn":[0.1981872627],"iteration":892,"passed_time":9.01748291,"remaining_time":1.080482275},
{"learn":[0.198026931],"iteration":893,"passed_time":9.027768534,"remaining_time":1.07040656},
{"learn":[0.1978208017],"iteration":894,"passed_time":9.038653011,"remaining_time":1.060400633},
{"learn":[0.1977132442],"iteration":895,"passed_time":9.049933336,"remaining_time":1.050438691},
{"learn":[0.1974827157],"iteration":896,"passed_time":9.061693128,"remaining_time":1.040528865},
{"learn":[0.1973935107],"iteration":897,"passed_time":9.071634728,"remaining_time":1.030408399},
{"learn":[0.1972043176],"iteration":898,"passed_time":9.081756465,"remaining_time":1.020308568},
{"learn":[0.1970182823],"iteration":899,"passed_time":9.094671213,"remaining_time":1.010519024},
{"learn":[0.1967217551],"iteration":900,"passed_time":9.104023852,"remaining_time":1.000331145},
{"learn":[0.1966026526],"iteration":901,"passed_time":9.113788693,"remaining_time":0.9901899024},
{"learn":[0.1964868625],"iteration":902,"passed_time":9.1229246,"remaining_time":0.9799819338},
{"learn":[0.1963612755],"iteration":903,"passed_time":9.131456867,"remaining_time":0.9697122336},
{"learn":[0.1961199551],"iteration":904,"passed_time":9.140055116,"remaining_time":0.9594532995},
{"learn":[0.1959261359],"iteration":905,"passed_time":9.149152982,"remaining_time":0.9492498679},
{"learn":[0.1957089435],"iteration":906,"passed_time":9.159150517,"remaining_time":0.9391411224},
{"learn":[0.1955953288],"iteration":907,"passed_time":9.168742951,"remaining_time":0.9289915766},
{"learn":[0.1954475842],"iteration":908,"passed_time":9.178221161,"remaining_time":0.9188318214},
{"learn":[0.1953520363],"iteration":909,"passed_time":9.187792264,"remaining_time":0.9086827514},
{"learn":[0.1951918754],"iteration":910,"passed_time":9.19648406,"remaining_time":0.8984490464},
{"learn":[0.195061286],"iteration":911,"passed_time":9.206792057,"remaining_time":0.8883746722},
{"learn":[0.1949209678],"iteration":912,"passed_time":9.216678995,"remaining_time":0.8782596633},
{"learn":[0.1945996309],"iteration":913,"passed_time":9.22709919,"remaining_time":0.8681953286},
{"learn":[0.1942967758],"iteration":914,"passed_time":9.236806984,"remaining_time":0.8580640367},
{"learn":[0.1941564902],"iteration":915,"passed_time":9.247062606,"remaining_time":0.8479839071},
{"learn":[0.1939786184],"iteration":916,"passed_time":9.25752892,"remaining_time":0.837922465},
{"learn":[0.1938814439],"iteration":917,"passed_time":9.27040371,"remaining_time":0.8280752769},
{"learn":[0.1937850402],"iteration":918,"passed_time":9.282335042,"remaining_time":0.8181383442},
{"learn":[0.1936220153],"iteration":919,"passed_time":9.292978812,"remaining_time":0.8080851141},
{"learn":[0.1934226694],"iteration":920,"passed_time":9.303398924,"remaining_time":0.798011417},
{"learn":[0.1931987258],"iteration":921,"passed_time":9.315348914,"remaining_time":0.7880663941},
{"learn":[0.1930162494],"iteration":922,"passed_time":9.325917041,"remaining_time":0.7780017467},
{"learn":[0.1928921323],"iteration":923,"passed_time":9.336857042,"remaining_time":0.7679665965},
{"learn":[0.1927917586],"iteration":924,"passed_time":9.347221333,"remaining_time":0.7578828108},
{"learn":[0.1927402626],"iteration":925,"passed_time":9.356692385,"remaining_time":0.7477270373},
{"learn":[0.192640283],"iteration":926,"passed_time":9.368033748,"remaining_time":0.7377200255},
{"learn":[0.1925175811],"iteration":927,"passed_time":9.378112138,"remaining_time":0.7276121486},
{"learn":[0.1923518248],"iteration":928,"passed_time":9.387391585,"remaining_time":0.717443275},
{"learn":[0.1922101781],"iteration":929,"passed_time":9.397420419,"remaining_time":0.7073327197},
{"learn":[0.1920826169],"iteration":930,"passed_time":9.406559248,"remaining_time":0.6971563782},
{"learn":[0.1919134965],"iteration":931,"passed_time":9.416041806,"remaining_time":0.6870073421},
{"learn":[0.1917999202],"iteration":932,"passed_time":9.424841504,"remaining_time":0.6768106975},
{"learn":[0.1916461149],"iteration":933,"passed_time":9.434641872,"remaining_time":0.6666877554},
{"learn":[0.1914714136],"iteration":934,"passed_time":9.4448897,"remaining_time":0.6565966102},
{"learn":[0.1913568609],"iteration":935,"passed_time":9.455715628,"remaining_time":0.6465446583},
{"learn":[0.191222444],"iteration":936,"passed_time":9.466266051,"remaining_time":0.6364725307},
{"learn":[0.1911505876],"iteration":937,"passed_time":9.477361155,"remaining_time":0.6264353855},
{"learn":[0.1910337933],"iteration":938,"passed_time":9.486568076,"remaining_time":0.6162733255},
{"learn":[0.1909375293],"iteration":939,"passed_time":9.495577101,"remaining_time":0.606100666},
{"learn":[0.1908663049],"iteration":940,"passed_time":9.505050154,"remaining_time":0.5959595739},
{"learn":[0.1907241335],"iteration":941,"passed_time":9.516090313,"remaining_time":0.5859163887},
{"learn":[0.1905517449],"iteration":942,"passed_time":9.525676448,"remaining_time":0.5757831999},
{"learn":[0.1903563319],"iteration":943,"passed_time":9.536205688,"remaining_time":0.5657071171},
{"learn":[0.1902683933],"iteration":944,"passed_time":9.545531691,"remaining_time":0.5555600455},
{"learn":[0.1902349005],"iteration":945,"passed_time":9.55375006,"remaining_time":0.5453514833},
{"learn":[0.1901179995],"iteration":946,"passed_time":9.563858059,"remaining_time":0.5352528798},
{"learn":[0.1899654359],"iteration":947,"passed_time":9.574405526,"remaining_time":0.5251783622},
{"learn":[0.189700371],"iteration":948,"passed_time":9.584765711,"remaining_time":0.5150927832},
{"learn":[0.1896480729],"iteration":949,"passed_time":9.594080503,"remaining_time":0.5049516054},
{"learn":[0.1894021759],"iteration":950,"passed_time":9.604060834,"remaining_time":0.4948464573},
{"learn":[0.1893146186],"iteration":951,"passed_time":9.613954722,"remaining_time":0.4847372129},
{"learn":[0.1891662358],"iteration":952,"passed_time":9.62301017,"remaining_time":0.4745870703},
{"learn":[0.1890522978],"iteration":953,"passed_time":9.633274748,"remaining_time":0.4644975245},
{"learn":[0.1887621523],"iteration":954,"passed_time":9.644378523,"remaining_time":0.4544471555},
{"learn":[0.18870877],"iteration":955,"passed_time":9.654061878,"remaining_time":0.4443292078},
{"learn":[0.1886162367],"iteration":956,"passed_time":9.664142314,"remaining_time":0.4342300099},
{"learn":[0.1881681563],"iteration":957,"passed_time":9.676678573,"remaining_time":0.4242385178},
{"learn":[0.1879622008],"iteration":958,"passed_time":9.686253926,"remaining_time":0.4141151313},
{"learn":[0.1878801208],"iteration":959,"passed_time":9.695702625,"remaining_time":0.4039876094},
{"learn":[0.1875402373],"iteration":960,"passed_time":9.707624611,"remaining_time":0.3939618729},
{"learn":[0.1874480093],"iteration":961,"passed_time":9.717001089,"remaining_time":0.3838316439},
{"learn":[0.1873235344],"iteration":962,"passed_time":9.725889417,"remaining_time":0.3736842247},
{"learn":[0.1871490954],"iteration":963,"passed_time":9.734825594,"remaining_time":0.3635412048},
{"learn":[0.1869317709],"iteration":964,"passed_time":9.74427297,"remaining_time":0.3534192269},
{"learn":[0.18685554],"iteration":965,"passed_time":9.753246161,"remaining_time":0.343281956},
{"learn":[0.1867643093],"iteration":966,"passed_time":9.762722142,"remaining_time":0.333164251},
{"learn":[0.1866370516],"iteration":967,"passed_time":9.772367778,"remaining_time":0.3230534803},
{"learn":[0.1865414796],"iteration":968,"passed_time":9.781629863,"remaining_time":0.3129313991},
{"learn":[0.1864632428],"iteration":969,"passed_time":9.790868496,"remaining_time":0.3028103659},
{"learn":[0.1863605362],"iteration":970,"passed_time":9.799710379,"remaining_time":0.2926793007},
{"learn":[0.1862259238],"iteration":971,"passed_time":9.809349582,"remaining_time":0.2825738563},
{"learn":[0.186059298],"iteration":972,"passed_time":9.81920409,"remaining_time":0.2724753447},
{"learn":[0.1859607037],"iteration":973,"passed_time":9.828196959,"remaining_time":0.2623543336},
{"learn":[0.1857911961],"iteration":974,"passed_time":9.83828006,"remaining_time":0.2522635913},
{"learn":[0.1856634943],"iteration":975,"passed_time":9.848612258,"remaining_time":0.2421789899},
{"learn":[0.1855329704],"iteration":976,"passed_time":9.858438225,"remaining_time":0.2320819644},
{"learn":[0.1853316428],"iteration":977,"passed_time":9.870068544,"remaining_time":0.2220260818},
{"learn":[0.1852078695],"iteration":978,"passed_time":9.880471942,"remaining_time":0.2119406647},
{"learn":[0.185068443],"iteration":979,"passed_time":9.88986304,"remaining_time":0.2018339396},
{"learn":[0.1848769142],"iteration":980,"passed_time":9.900960349,"remaining_time":0.1917617193},
{"learn":[0.1848005779],"iteration":981,"passed_time":9.910729541,"remaining_time":0.1816630669},
{"learn":[0.1845771814],"iteration":982,"passed_time":9.920298121,"remaining_time":0.1715616155},
{"learn":[0.1844165476],"iteration":983,"passed_time":9.929403237,"remaining_time":0.1614537112},
{"learn":[0.1842593208],"iteration":984,"passed_time":9.939238999,"remaining_time":0.1513589695},
{"learn":[0.184134955],"iteration":985,"passed_time":9.94827266,"remaining_time":0.1412533643},
{"learn":[0.1839886921],"iteration":986,"passed_time":9.957982263,"remaining_time":0.1311588343},
{"learn":[0.1838291314],"iteration":987,"passed_time":9.967314417,"remaining_time":0.121060499},
{"learn":[0.183623013],"iteration":988,"passed_time":9.976321237,"remaining_time":0.1109600946},
{"learn":[0.183489805],"iteration":989,"passed_time":9.985735793,"remaining_time":0.1008660181},
{"learn":[0.1832887698],"iteration":990,"passed_time":9.994424604,"remaining_time":0.09076672193},
{"learn":[0.183142092],"iteration":991,"passed_time":10.0041099,"remaining_time":0.08067830562},
{"learn":[0.1830921177],"iteration":992,"passed_time":10.01307927,"remaining_time":0.07058565449},
{"learn":[0.1829540158],"iteration":993,"passed_time":10.02241029,"remaining_time":0.06049744641},
{"learn":[0.1827149793],"iteration":994,"passed_time":10.03375951,"remaining_time":0.05042090207},
{"learn":[0.1825609513],"iteration":995,"passed_time":10.04396322,"remaining_time":0.04033720167},
{"learn":[0.1824150283],"iteration":996,"passed_time":10.05483628,"remaining_time":0.03025527465},
{"learn":[0.1822679143],"iteration":997,"passed_time":10.06877341,"remaining_time":0.02017790262},
{"learn":[0.1820967657],"iteration":998,"passed_time":10.07913472,"remaining_time":0.01008922394},
{"learn":[0.1819419633],"iteration":999,"passed_time":10.09053201,"remaining_time":0}
]}